{
  "kind": "youtube#playlistItemListResponse",
  "etag": "NnpzzP3TT1bOQfOa9Co2E43Rtic",
  "items": [
    {
      "kind": "youtube#playlistItem",
      "etag": "6yGrI1LO-0brGljyuTbfxTxaNJE",
      "id": "UEx6SjFtcXd4b2dwRnVGQ2sxWWZVRTFjMGdXdG5JdXRmei4wMTcyMDhGQUE4NTIzM0Y5",
      "snippet": {
        "publishedAt": "2024-02-06T03:55:39Z",
        "channelId": "UCZtzcQ_fiXuw6dNx_AxK7_Q",
        "title": "ロクデナシ「愛が灯る」/ Rokudenashi - The Flame of Love【Official Music Video】",
        "description": "2023.02.15 Release\nStreaming＆Download ▶ https://rokudenashi-ninzin.lnk.to/Aigatomoru\n\nInstrumental＜ピアプロ＞：https://piapro.jp/t/U-jm\nPiano Score＜PDF＞：https://22.gigafile.nu/0221-d0abc9b52960864f6fc58d207c69e1878\n\n1st Album「愛ニ咲花」2023.12.27 Release\n▶︎ https://Rokudenashi-ninzin.jp/special/\n\nTwitter：https://twitter.com/Rokudenashi_nzn\nInstagram：https://www.instagram.com/rokudenashi_ninzin/\nTikTok：https://www.tiktok.com/@rokudenashi_ninzin\n\nVocal：にんじん @ninzin_official \nWords, Music & Arrangement：MIMI @MIMI...official \nIllustration：faPka（ https://twitter.com/fapkapukapuka ）\nMovie：よしだなすび（ https://twitter.com/Yoshidanasubeam ）\nMix Engineer：Chikara Sato（ https://twitter.com/studioonett ）\nMastering Engineer：Tsubasa Yamazaki\n\n#ロクデナシ #愛が灯る #にんじん",
        "thumbnails": {
          "default": {
            "url": "https://i.ytimg.com/vi/_XeE2aEiPHk/default.jpg",
            "width": 120,
            "height": 90
          },
          "medium": {
            "url": "https://i.ytimg.com/vi/_XeE2aEiPHk/mqdefault.jpg",
            "width": 320,
            "height": 180
          },
          "high": {
            "url": "https://i.ytimg.com/vi/_XeE2aEiPHk/hqdefault.jpg",
            "width": 480,
            "height": 360
          },
          "standard": {
            "url": "https://i.ytimg.com/vi/_XeE2aEiPHk/sddefault.jpg",
            "width": 640,
            "height": 480
          },
          "maxres": {
            "url": "https://i.ytimg.com/vi/_XeE2aEiPHk/maxresdefault.jpg",
            "width": 1280,
            "height": 720
          }
        },
        "channelTitle": "Synera",
        "playlistId": "PLzJ1mqwxogpFuFCk1YfUE1c0gWtnIutfz",
        "position": 0,
        "resourceId": {
          "kind": "youtube#video",
          "videoId": "_XeE2aEiPHk"
        },
        "videoOwnerChannelTitle": "ロクデナシ / Rokudenashi",
        "videoOwnerChannelId": "UCRlRgAguUGfWD4EDfBUls4w"
      }
    },
    {
      "kind": "youtube#playlistItem",
      "etag": "E8JknsbS8qI-j0A5ZZ7fflYwjMQ",
      "id": "UEx6SjFtcXd4b2dwRnVGQ2sxWWZVRTFjMGdXdG5JdXRmei41MjE1MkI0OTQ2QzJGNzNG",
      "snippet": {
        "publishedAt": "2024-02-06T03:55:48Z",
        "channelId": "UCZtzcQ_fiXuw6dNx_AxK7_Q",
        "title": "Novelbright - 愛とか恋とか [Official Music Video]",
        "description": "2022.5.18 Release\nMajor 2nd Full Album「Assort」リード曲「愛とか恋とか」\nStreaming&DL▶️https://novelbright.lnk.to/AitokaKoitoka\n各種音楽配信&サブスクリプションサービスで配信中！\n\n----------------------------------------------------------------------------------------------\nMajor 2nd Full Album「Assort」\n予約受付中▶https://novelbright.lnk.to/Assort_Reserve\n----------------------------------------------------------------------------------------------\n2024年4月6日(土)北海道公演から始まる全国ワンマンツアー\n「Novelbright LIVE TOUR 2024 ～CIRCUS～」開催！\n多くの公演がSOLD OUT！4/12(金)山口公演のみチケットあります\n\n■各プレイガイド一般発売中！\n受付期間：2月3日(土)10:00～\n【チケット】\n全席指定      　　 　  :￥7,000(税込)\n全席指定【学割】　　　 :￥4,900（税込）\n\nチケットぴあ：https://w.pia.jp/t/novelbright/\nイープラス：https://eplus.jp/novelbright/\nローソンチケット：https://l-tike.com/novelbright/\n\n●5/22(水)東京・8/5(月)北海道追加公演のFC2次抽選先行が4/2(火)18時より開始！\n詳細はHPご覧ください\n受付期間：4/2(火)18:00～4/7(日)23:59\nhttps://novelbright.jp/news/detail/1790\n\n4月6日(土)　 【北海道】 カナモトホール\n4月12日(金)  【山口県】KDDI維新ホール メインホール\n4月14日(日)  【広島県】呉信用金庫ホール(呉市文化ホール)\n4月19日(金)  【香川県】サンポートホール高松 大ホール\n4月20日(土)  【愛媛県】松山市民会館 大ホール\n4月27日(土)  【群馬県】高崎芸術劇場 大劇場\n4月29日(月祝)【栃木県】栃木県総合文化センター メインホール\n5月2日(木)   【愛知県】名古屋国際会議場センチュリーホール\n5月10日(金)  【福井県】鯖江市文化センター\n5月17日(金)  【福島県】白河文化交流館コミネス 大ホール\n5月22日(水)　【東京都】Zepp DiverCity(TOKYO) ※追加公演\n5月24日(金)  【福岡県】福岡市民会館\n5月26日(日)  【京都府】文化パルク城陽 プラムホール\n6月1日(土) 　【岡山県】岡山芸術創造劇場ハレノワ 大劇場\n6月2日(日) 　【島根県】出雲市民会館 大ホール\n6月6日(木) 　【大阪府】オリックス劇場\n6月8日(土) 　【静岡県】静岡市民文化会館 中ホール\n6月15日(土)  【宮崎県】都城市総合文化ホール 大ホール\n6月16日(日)  【佐賀県】鳥栖市民文化会館\n6月21日(金)  【石川県】本多の森 北電ホール\n6月23日(日)  【岐阜県】岐阜市民会館 大ホール\n6月28日(金)  【奈良県】なら100年会館 大ホール\n6月30日(日)  【滋賀県】守山市民ホール 大ホール\n7月6日(土) 　【山形県】酒田市民会館(希望ホール) 大ホール\n7月7日(日) 　【宮城県】トークネットホール仙台(仙台市民会館)\n7月26日(金)  【東京都】東京ガーデンシアター\n8月5日(月)　 【北海道】カナモトホール ※追加公演\n----------------------------------------------------------------------------------------------\n\nCast：Nagisa Sekimizu / Yuto Oku\nDirector / Editor：ill.pics\nDirector of Photography：ill.pics\nAssistant camera：Junpei Azuma / Takeyuki furuhashi\nLighting Director：Ryuji Matsumoto\nLighting Assistant：Nanae Niwa / Shinya Ishikawa\nHairmake(Novelbright)：STORM (LINX)\nStylist(Novelbright)：Haruki Okamura\nHairmake(Cast)：Madoka ban / Natsuki Takahata\nStylist (Cast)：Mei Komiyama\nAssistant Stylist(Cast)：Mana Kaneishi\nProducer：Yukiko Yamamoto\nProducion Manager：Ruka Kuriwaki\nProduction Assistant：Akiko Tachikawa / Kaho Harada\nLocation：NPO teganumaFilm commission / hermitclub.\nProduction：UNITED PRODUCTIONS\n\n#Novelbright #愛とか恋とか #関水渚",
        "thumbnails": {
          "default": {
            "url": "https://i.ytimg.com/vi/Q5JytNgQzqk/default.jpg",
            "width": 120,
            "height": 90
          },
          "medium": {
            "url": "https://i.ytimg.com/vi/Q5JytNgQzqk/mqdefault.jpg",
            "width": 320,
            "height": 180
          },
          "high": {
            "url": "https://i.ytimg.com/vi/Q5JytNgQzqk/hqdefault.jpg",
            "width": 480,
            "height": 360
          },
          "standard": {
            "url": "https://i.ytimg.com/vi/Q5JytNgQzqk/sddefault.jpg",
            "width": 640,
            "height": 480
          },
          "maxres": {
            "url": "https://i.ytimg.com/vi/Q5JytNgQzqk/maxresdefault.jpg",
            "width": 1280,
            "height": 720
          }
        },
        "channelTitle": "Synera",
        "playlistId": "PLzJ1mqwxogpFuFCk1YfUE1c0gWtnIutfz",
        "position": 1,
        "resourceId": {
          "kind": "youtube#video",
          "videoId": "Q5JytNgQzqk"
        },
        "videoOwnerChannelTitle": "Novelbright",
        "videoOwnerChannelId": "UCIJAlAYCNN8RACtDDsy9K6g"
      }
    },
    {
      "kind": "youtube#playlistItem",
      "etag": "kNegcsgDM5e0mTD0Bn--SwBLUwM",
      "id": "UEx6SjFtcXd4b2dwRnVGQ2sxWWZVRTFjMGdXdG5JdXRmei4wOTA3OTZBNzVEMTUzOTMy",
      "snippet": {
        "publishedAt": "2024-02-06T03:56:46Z",
        "channelId": "UCZtzcQ_fiXuw6dNx_AxK7_Q",
        "title": "西野カナ『もしも運命の人がいるのなら』Live on \"Love Collection Live 2019\"",
        "description": "『もしも運命の人がいるのなら』のLive on Love Collection Live 2019をYouTube初公開！！\nST/DLはこちらhttps://nishinokana.lnk.to/Moshimounnmeinohitogairunonara\n\n『もしも運命の人がいるのなら』\n2015年4月発売Sg\n2016年7月発売AL「Just LOVE」収録\n2018年11月発売BEST AL「Love Collection 2 ～mint～」収録\n\n“Kana Nishino Love Collection Live 2019”より 映像商品購入はこちらから 　2019年＠横浜アリーナ\nhttps://www.sonymusicshop.jp/m/item/itemShw.php?site=S&cd=SEXL000000130\n\n『もしも運命の人がいるのなら』 作詞：西野カナ\n\n一分一秒 今この瞬間も\n世界のどこかで誰かがきっと\n恋に落ちてく 結ばれていく\nたったひとりの運命の人と\n\nかっこよくて 爽やかで\n私よりも背が高くて\n笑顔が素敵で Ah\nキリがない理想 結局は\n「好きになった人がタイプ」\nそういうもんでしょ\n\nそれでも昔から\n好きな人には好かれないし\nいいなと思った人は\n恋人がいるわ\n\nもしも運命の人がいるのなら\n運命の出会いがあるなら\nあなたはいったい\nどこで寄り道しているのかしら？\nもしかしたらすぐ近くにいる？\nそれとも遥か海の向こう？\nいつかあなたが迎えに来てくれる\nその日まで待っているから\n\nやっぱり優しい人がいい\nもちろんそれはそうだけど\n優しいだけじゃ Ah\n「俺についてこい」と言われても\n黙ってはついて行けないし\nこれってワガママかな？\n\n中身が大事だって\n初対面じゃ分からないし\n勢いも大事だって\n妥協もできないわ\n\nもしも運命の人がいるのなら\n運命の出会いがあるなら\nあなたはいったい\nいつになれば辿り着くのかしら？\n占いでは昨日のはずだけど\n明日か明後日か来年かな？\nいつかあなたが迎えに来てくれる\nその日まで待っているから\n\n\n一分一秒 今この瞬間も\n運命のその時に近づいてる\n夢を見ている いつかあなたと\nたったひとりの運命の人と\n\nもしも運命の人がいるのなら\n運命の出会いがあるなら\nあなたはいったい\nどこで寄り道しているのかしら？\n私ならずっとここにいるよ\nそろそろ待ちくたびれる頃\n風のうわさではまた誰かが\n運命の人に出逢ったみたい\nあなたが迎えに来てくれる\nその日まで やっぱり… 待てないわ\n\n■西野カナ サブスク・ダウンロード\nhttps://nishinokana.lnk.to/DLST\n■西野カナ CD・DVD・Blu-rayパッケージ\nhttps://www.sonymusicshop.jp/m/arti/artiItm.php?site=S&ima=3019&cd=70005022\n■西野カナOfficial Site\nhttp://www.nishinokana.com/\n■公式SNS\n[Twitter] https://twitter.com/kanayanofficial\n[Facebook] https://ja-jp.facebook.com/nishinokanaofficial\n\n#西野カナサブスク全曲解禁 #恋する気持ちをもう一度",
        "thumbnails": {
          "default": {
            "url": "https://i.ytimg.com/vi/RFFzHTHEiq8/default.jpg",
            "width": 120,
            "height": 90
          },
          "medium": {
            "url": "https://i.ytimg.com/vi/RFFzHTHEiq8/mqdefault.jpg",
            "width": 320,
            "height": 180
          },
          "high": {
            "url": "https://i.ytimg.com/vi/RFFzHTHEiq8/hqdefault.jpg",
            "width": 480,
            "height": 360
          },
          "standard": {
            "url": "https://i.ytimg.com/vi/RFFzHTHEiq8/sddefault.jpg",
            "width": 640,
            "height": 480
          },
          "maxres": {
            "url": "https://i.ytimg.com/vi/RFFzHTHEiq8/maxresdefault.jpg",
            "width": 1280,
            "height": 720
          }
        },
        "channelTitle": "Synera",
        "playlistId": "PLzJ1mqwxogpFuFCk1YfUE1c0gWtnIutfz",
        "position": 2,
        "resourceId": {
          "kind": "youtube#video",
          "videoId": "RFFzHTHEiq8"
        },
        "videoOwnerChannelTitle": "西野カナ Official YouTube Channel",
        "videoOwnerChannelId": "UCXq19VXLNkTtVE9LfRBKd5Q"
      }
    },
    {
      "kind": "youtube#playlistItem",
      "etag": "EmcS1D6wt9T4Q6gxX4VdAcfdMVk",
      "id": "UEx6SjFtcXd4b2dwRnVGQ2sxWWZVRTFjMGdXdG5JdXRmei41MzJCQjBCNDIyRkJDN0VD",
      "snippet": {
        "publishedAt": "2024-02-06T03:58:10Z",
        "channelId": "UCZtzcQ_fiXuw6dNx_AxK7_Q",
        "title": "LiSA 『炎』 -MUSiC CLiP-",
        "description": "「炎」（劇場版「鬼滅の刃」無限列車編 主題歌）\nDOWNLOAD & STREAMING\nhttps://LiSA.lnk.to/homura_digital \n\n「炎」\n作詞：梶浦由記、LiSA\n作曲：梶浦由記\n編曲：梶浦由記\n\nLiSA 6th Album 「LANDER」\n発売日：2022年11月16日（水）\n\nCD：https://lisa.lnk.to/LANDER_pkg\n\n●完全数量生産限定盤（CD+GOODS）\nVVCL 2120-1 / 9,350円（税込）\n●初回生産限定盤A（CD+Blu-ray+PHOTOBOOK）\nVVCL 2122-4 / 5,720円（税込）\n●初回生産限定盤B（CD+DVD＋PHOTOBOOK）\nVVCL 2125-7 / 5,720円（税込）\n●通常盤（CD）\nVVCL 2128 / 3,300円（税込）\n\n[CD収録内容] 全形態共通\n01.往け\n（「劇場版 ソードアート・オンライン - プログレッシブ - 星なき夜のアリア」主題歌）\n02.一斉ノ喝采\n　（ABEMA・テレビ朝日 FIFA ワールドカップ カタール 2022 番組公式テーマソング）\n03.dis/connect\n04.シャンプーソング\n05.明け星\n（テレビアニメ「鬼滅の刃」無限列車編 オープニングテーマ）\n06.白銀\n（テレビアニメ「鬼滅の刃」無限列車編 エンディングテーマ）\n07.炎\n（劇場版「鬼滅の刃」無限列車編 主題歌）\n08.逃飛行\n09.HADASHi NO STEP\n（TBS系 火曜ドラマ「プロミス・シンデレラ」主題歌）\n10.シフクノトキ\n（カバヤ・ピュアラルグミCMソング）\n11.土曜日のわたしたちは\n（日本テレビ系「ズームイン‼️サタデー」テーマソング）\n12.悪女のオキテ\n13.dawn\n（TVアニメ「バック・アロウ」 オープニングテーマ）\n14.NEW ME\n\nLiSA - 炎 / THE FIRST TAKE\nhttps://www.youtube.com/watch?v=4Q9DWZLaY2U \n\nFollow LiSA\nOFFICIAL WEBSITE：http://www.lxixsxa.com/\nLiSA Twitter：https://twitter.com/LiSA_OLiVE\nLiSA STAFF Twitter：https://twitter.com/LiSA_STAFF\nFacebook：https://www.facebook.com/lxixsxa.jp/\nInstagram：https://www.instagram.com/xlisa_olivex/\nTikTok：https://www.tiktok.com/@lxixsxa_official\n\n#LiSA #炎 #鬼滅の刃 #Homura #DemonSlayer",
        "thumbnails": {
          "default": {
            "url": "https://i.ytimg.com/vi/4DxL6IKmXx4/default.jpg",
            "width": 120,
            "height": 90
          },
          "medium": {
            "url": "https://i.ytimg.com/vi/4DxL6IKmXx4/mqdefault.jpg",
            "width": 320,
            "height": 180
          },
          "high": {
            "url": "https://i.ytimg.com/vi/4DxL6IKmXx4/hqdefault.jpg",
            "width": 480,
            "height": 360
          },
          "standard": {
            "url": "https://i.ytimg.com/vi/4DxL6IKmXx4/sddefault.jpg",
            "width": 640,
            "height": 480
          },
          "maxres": {
            "url": "https://i.ytimg.com/vi/4DxL6IKmXx4/maxresdefault.jpg",
            "width": 1280,
            "height": 720
          }
        },
        "channelTitle": "Synera",
        "playlistId": "PLzJ1mqwxogpFuFCk1YfUE1c0gWtnIutfz",
        "position": 3,
        "resourceId": {
          "kind": "youtube#video",
          "videoId": "4DxL6IKmXx4"
        },
        "videoOwnerChannelTitle": "LiSA Official YouTube",
        "videoOwnerChannelId": "UCqEfdEvLG5oQWNYlDQrGlKw"
      }
    },
    {
      "kind": "youtube#playlistItem",
      "etag": "lzkDqnAh-6QlWwVeQ70nOxjQRDk",
      "id": "UEx6SjFtcXd4b2dwRnVGQ2sxWWZVRTFjMGdXdG5JdXRmei5DQUNERDQ2NkIzRUQxNTY1",
      "snippet": {
        "publishedAt": "2024-02-06T03:58:18Z",
        "channelId": "UCZtzcQ_fiXuw6dNx_AxK7_Q",
        "title": "Aimer「残響散歌」MUSIC VIDEO（テレビアニメ「鬼滅の刃」遊郭編オープニングテーマ）",
        "description": "テレビアニメ「鬼滅の刃」遊郭編OPテーマ&EDテーマAimer 『残響散歌/朝が来る』now on sale!⇒https://aimer.lnk.to/zankyosanka\n\nAimer 20th single 『残響散歌/朝が来る』\n発売日：2022年1月12日（水）\n「残響散歌」…テレビアニメ「鬼滅の刃」遊郭編オープニングテーマ\n「朝が来る」…テレビアニメ「鬼滅の刃」遊郭編エンディングテーマ\n\n初回生産限定盤（CD+DVD）\n1,760円（税込）/ VVCL-1953-1954\n※CD+DVD（「残響散歌」「朝が来る」MUSIC VIDEO収録）\n\n通常盤（CD）\n1,320円（税込）/ VVCL-1955\n期間生産限定盤（CD+DVD）\n\n1,760円（税込）/ VVCL-1956-1957\n※テレビアニメ「鬼滅の刃」遊郭編描きおろしジャケット\n※テレビアニメ「鬼滅の刃」遊郭編描きおろしイラスト使用ミニポスター\n※テレビアニメ「鬼滅の刃」遊郭編ノンクレジットOP/ED映像収録\n\n#Aimer #鬼滅の刃　＃遊郭編\n\n「残響散歌」MUSIC VIDEO\nDirector：YASUHIRO ARAFUNE (EPOCH)\nProducer：NAOKI AKIYAMA (19-juke-)\nCast：Mayuki\n\nhttp://www.aimer-web.jp/",
        "thumbnails": {
          "default": {
            "url": "https://i.ytimg.com/vi/tLQLa6lM3Us/default.jpg",
            "width": 120,
            "height": 90
          },
          "medium": {
            "url": "https://i.ytimg.com/vi/tLQLa6lM3Us/mqdefault.jpg",
            "width": 320,
            "height": 180
          },
          "high": {
            "url": "https://i.ytimg.com/vi/tLQLa6lM3Us/hqdefault.jpg",
            "width": 480,
            "height": 360
          },
          "standard": {
            "url": "https://i.ytimg.com/vi/tLQLa6lM3Us/sddefault.jpg",
            "width": 640,
            "height": 480
          }
        },
        "channelTitle": "Synera",
        "playlistId": "PLzJ1mqwxogpFuFCk1YfUE1c0gWtnIutfz",
        "position": 4,
        "resourceId": {
          "kind": "youtube#video",
          "videoId": "tLQLa6lM3Us"
        },
        "videoOwnerChannelTitle": "Aimer Official YouTube Channel",
        "videoOwnerChannelId": "UCR1zT1s524Hbc85bdvno_8w"
      }
    },
    {
      "kind": "youtube#playlistItem",
      "etag": "1hK5jgIpNZaPX54k8HJZx1V957w",
      "id": "UEx6SjFtcXd4b2dwRnVGQ2sxWWZVRTFjMGdXdG5JdXRmei45NDk1REZENzhEMzU5MDQz",
      "snippet": {
        "publishedAt": "2024-02-14T02:59:54Z",
        "channelId": "UCZtzcQ_fiXuw6dNx_AxK7_Q",
        "title": "【女性が歌う】幸せ / back number(Covered by コバソロ & 藤川千愛)",
        "description": "今回はback numberの幸せをカバーしました。今回のボーカルは藤川千愛さん！チャンネル登録してね！▶︎ https://www.youtube.com/user/Hujikoman\n\n【藤川千愛】\nTwitter:  https://twitter.com/fujikawachiai\nInstagram:  https://www.instagram.com/fujikawa_chiai/\nYoutube:  https://www.youtube.com/channel/UCPn4XA6Gb2u8y_FXXtrHW7w\n音楽配信:  https://nippon-columbia.lnk.to/9GTDu\nOfficial HP:  https://fujikawachiai.com/\n\n【RELEASE INFORMATION】\n⚫︎⚫︎⚫︎⚫︎⚫︎Original⚫︎⚫︎⚫︎⚫︎⚫︎\n\n★2019.3.26 Release!!\n配信限定2nd album「Clumsy」\n1500円\n配信サイト一覧→https://linkco.re/prxtScat\n収録曲\nM1 どうか幸せにならないで feat. 春茶\nM2 新世界のユーツ feat. SiN\nM3 会いたくて feat. こぴ\nM4 夏恋慕 feat. 春茶\nM5 春に揺られど君想う feat. こぴ\nM6 ラブレター feat. 春茶\nM7 言葉さがし feat. こぴ & SiN\nM8 outro\n\n★1st full album「KOBASOLO」\n配信サイト一覧→ https://linkco.re/cy6VH9VX\nCD通販→ https://kobasolo.stores.jp\n\n⚫︎⚫︎⚫︎⚫︎⚫︎Cover⚫︎⚫︎⚫︎⚫︎⚫︎\n\n★2nd Cover Album「これくしょん２」NEW!!\n配信サイト一覧→ https://vap.lnk.to/collection2\nAmazon→ https://www.amazon.co.jp/dp/B07KZ1Y2Q5/ref=cm_sw_r_tw_dp_U_x_Dd1FCbA45JPNM\n全国CDショップやAmazon、楽天などでも発売中!!\n\n★1st Cover Album「これくしょん」\n配信サイト一覧→ https://vap.lnk.to/correction\nAmazon→ https://www.amazon.co.jp/dp/B073WSPGM5/ref=cm_sw_r_tw_dp_U_x_Se1FCbV3TWWHN\n全国CDショップやAmazon、楽天などでも発売中!!\n\n★コバソロ & 未来 \n配信限定EP「MIRAI COVERS」\n配信サイト一覧→ https://umj.lnk.to/zxNBB\n\n★Cover Album「これくしょん」特設サイトhttp://www.vap.co.jp/kobasolo/\n\n⚫︎⚫︎⚫︎⚫︎⚫︎⚫︎⚫︎⚫︎⚫︎⚫︎⚫︎⚫︎⚫︎⚫︎⚫︎⚫︎⚫︎⚫︎⚫︎⚫︎⚫︎⚫︎⚫︎⚫︎⚫︎⚫︎⚫︎⚫︎⚫︎⚫︎⚫︎⚫︎⚫︎⚫︎⚫︎\n\n【コバソロ/Kobasolo】\nYouTube▶︎http://www.youtube.com/user/Hujikoman\n2ndチャンネル▶︎https://goo.gl/FuH0aR\nTwitter▶︎https://twitter.com/kobamakolts\nfacebook▶︎http://www.facebook.com/#!/kobasolo\ninstagram▶︎http://instagram.com/kobasolo/\nHP▶︎http://kobasolo.net/\nオンラインショップ▶︎https://kobasolo.stores.jp\n\n【オリジナル曲MV】\n★エンディング曲\n『君さえいなけりゃ feat. 春茶/コバソロ』\niTunes▶︎https://apple.co/2jMiMvi\nMV▶︎https://youtu.be/-KOeQapXsx8\n\n【使用機材】───────────────\n●カメラ(2012〜2016)https://amzn.to/2U54NEF\n● カメラ(2017〜)https://amzn.to/2Wf6v3F\nhttps://amzn.to/2JqOw8T\n\n●レンズ\nhttps://amzn.to/2WdXqYN\nhttps://amzn.to/2Jrs7Ik\nhttps://amzn.to/2HL91dN\n\n●スタビライザー\nhttps://amzn.to/2FoeUfs\nhttps://amzn.to/2Wdf9zC\n\n●照明\nhttps://amzn.to/2HJ6IYK\nhttps://amzn.to/2WdIxWb\n\n●DTMソフト\nhttps://amzn.to/2TNEcwd\n\n●ヘッドホン\nhttps://amzn.to/2Fo5CAc\n\n●オーディオインターフェース\nhttps://amzn.to/2FpX7ok\n\n●コンデンサーマイク\nhttps://amzn.to/2TWRKVp\nhttps://amzn.to/2W6vc1S\n\n※上記製品リンクURLはAmazonアソシエイトのリンクを使用しています。\n\n■─────────────────────────────────■\nThis video is\nFilmed by kobasolo\nEdited by kobasolo\nAudio produced by kobasolo\n#藤川千愛 #盾の勇者の成り上がり #backnumber",
        "thumbnails": {
          "default": {
            "url": "https://i.ytimg.com/vi/ruxJacIFKL4/default.jpg",
            "width": 120,
            "height": 90
          },
          "medium": {
            "url": "https://i.ytimg.com/vi/ruxJacIFKL4/mqdefault.jpg",
            "width": 320,
            "height": 180
          },
          "high": {
            "url": "https://i.ytimg.com/vi/ruxJacIFKL4/hqdefault.jpg",
            "width": 480,
            "height": 360
          },
          "standard": {
            "url": "https://i.ytimg.com/vi/ruxJacIFKL4/sddefault.jpg",
            "width": 640,
            "height": 480
          },
          "maxres": {
            "url": "https://i.ytimg.com/vi/ruxJacIFKL4/maxresdefault.jpg",
            "width": 1280,
            "height": 720
          }
        },
        "channelTitle": "Synera",
        "playlistId": "PLzJ1mqwxogpFuFCk1YfUE1c0gWtnIutfz",
        "position": 5,
        "resourceId": {
          "kind": "youtube#video",
          "videoId": "ruxJacIFKL4"
        },
        "videoOwnerChannelTitle": "kobasolo",
        "videoOwnerChannelId": "UCDbQblY1XASbgqOXmy6FOFQ"
      }
    },
    {
      "kind": "youtube#playlistItem",
      "etag": "eJBM1bwIyzk_o3jg6CZEkhRL-N0",
      "id": "UEx6SjFtcXd4b2dwRnVGQ2sxWWZVRTFjMGdXdG5JdXRmei5GNjNDRDREMDQxOThCMDQ2",
      "snippet": {
        "publishedAt": "2024-02-20T02:31:48Z",
        "channelId": "UCZtzcQ_fiXuw6dNx_AxK7_Q",
        "title": "あいみょん – 桜が降る夜は【OFFICIAL MUSIC VIDEO】",
        "description": "2月17日(水)より配信中の「桜が降る夜は」MV公開！\nABEMA『オオカミ』シリーズ最新作『恋とオオカミには騙されない』主題歌！\n\n\n【MOVIE】\nDirector：Tomokazu Yamada\nDirector of Photography：Keisuke Imamura\nLighting Director：Ryuto Iwabuchi\nProduction Designer: Yui Miyamori\nStylist：Chie Ninomiya\nHair&Make-up：Masaki Sugaya\nSteadicam Operator：Takuma Iwata\nSpecial Effects：Kenji Kawaguchi (KIKKOSEN)\nOnline Editor：Shunsuke Endo (Kicks)\nColorist：Masahiro Ishiyama  (DEGITAL GARDEN)\nTitle Design：Rak (TM INC.)\nCamera Chief Assistant：Yamato Sugimoto\nCamera Assistant：Shintaro Higuchi／Kakeru Sudo\nSteadicam Assistant：Akira Hayakawa\nLighting Chief Assistant：Shinkichi Komatsu\nLighting Assistant：Yuki Ogawa／Nagomi Oosaki／Tomoki Yamada／Koji Sato\nProduction Designer Assistant：Seita Oyama\nStylist Assistant：Yoshie Nunoda\nSpecial Effects Assistant：Kensaku Harayama (KIKKOSEN)／Kazuaki Watanabe (KIKKOSEN)\nColorist Assistant：Minai Miku  (DEGITAL GARDEN)\nHigh Rider : Koishi Kawamura (Black Out)\nTransporter：Junichiro Ikuta／Suguru Sakai\nMaking Director：Akari Eda\nProduction Manager：Shun Ikeda\nProduction Manager Assistant：Minami Hayashi, Masamitsu Wakimoto\nProducer：Takanobu Oki\nProduction：CROMANYON\nSpecial Thanks：NINGEN RESTURANT／KARAOKEKAN／KOKIHIFUMI／ARC•SYSTEM\n\n\n【MUSIC】\nsound produced by 田中ユウスケ(agehasprings)\nproduced by POTATO PRODUCTIONS\narrangement, programming & all other instruments : 近藤隆史･立崎優介(Q.,Ltd), 田中ユウスケ\nelectric guitar : 八橋義幸\nbass : 中西道彦(Yasei Collective)\ndrums : 伊吹文裕\nprogramming : 高倉壮一郎\nacoustic guitar : あいみょん\nstrings arrange : 室屋光一郎\n1st violin : 室屋光一郎\n2nd violin : 徳永友美\nviola : 島岡智子\nvioloncello : 水野由紀\nrecorded by 中村 督(POTATO STUDIO), 田宮 空(MIXER'S LAB)\nrecorded at SOUND CREW STUDIO, LAB recorders\nmixed by 中村 督\nmixed at Aobadai studio, POTATO STUDIO\nassisted by 斉藤公平(SOUND CREW STUDIO), 渡邊啓太(MIXER'S LAB), 吉井雅之・黒田花穂(Aobadai studio)\nmastered by 南石聡巳(duskline recording studio)\nPOTATO PRODUCTIONS(中村 督･高倉壮一郎･田中ユウスケ)\n\n\n【配信リリース情報】\n「桜が降る夜は」\n配信日：2月17日（水）\n\n各配信先はこちら\nhttps://aim.lnk.to/cherryblossom\n\nあいみょん – 桜が降る夜は【very short movie】\nhttps://youtu.be/YXe7GQnvzqY\n\n「桜が降る夜は」Instagram ARフィルターも公開中！\nhttps://www.instagram.com/ar/912980039528813/\n\n\n【番組概要】\nABEMA『オオカミ』シリーズ最新作『恋とオオカミには騙されない』\n配信日時：毎週日曜日夜10時～\n\n「ABEMA」URL：https://abema.tv/video/episode/90-1478_s99_p2\n第1話配信 URL：https://abema.tv/channels/abema-special/slots/8TNjdQ1Xiy7Uaj\n公式Twitter：https://twitter.com/ookami_official\n公式Instagram：https://www.instagram.com/ookami_official/\n公式TikTok：https://www.tiktok.com/@ookami_official\n\n\n【CDリリース情報】\n3rdアルバム「おいしいパスタがあると聞いて」\n発売日：2020年9月9日（水）\n\n購入＆配信リンク\nhttps://aim.lnk.to/oishiipasta\n\n品番／金額：\n\n〔通常盤〕\nWPCL-13210\n¥2,800（税抜）\n\n〔初回限定盤〕\nWPCL-13235～6\n¥4,000（税抜） \n\n収録内容\n〔DISC-1（CD）〕\n※収録内容初回限定盤・通常盤共通※\n01 黄昏にバカ話をしたあの日を思い出す時を\n02 ハルノヒ\n03 シガレット\n04 さよならの今日に\n05 朝陽\n06 裸の心\n07 マシマロ\n08 空の青さを知る人よ\n09 真夏の夜の匂いがする\n10 ポプリの葉\n11 チカ\n12 そんな風に生きている\n\n〔DISC-2（CD）〕※初回限定盤\n01 ふたりの世界\n02 愛を伝えたいだとか\n03 サラバ\n04 二人だけの国\n05 ハッピー\n06 葵\n07 ハルノヒ\n08 裸の心\n09 マリーゴールド\n10 青春と青春と青春\n\n●”「風とリボン - POTATO STUDIO, June, 2020 -」 behind the scenes”　DAY1\nhttps://youtu.be/LesY2BeILcc\n\n●”「風とリボン - POTATO STUDIO, June, 2020 -」 behind the scenes”　DAY2\nhttps://youtu.be/V-KarrdAuV4\n\n●”「風とリボン - POTATO STUDIO, June, 2020 -」 behind the scenes”　DAY3\nhttps://youtu.be/N1EmO9xDBAs\n\nあいみょん – おいしいパスタがあると聞いて【very short teaser】\nhttps://youtu.be/2V3R1699A_0",
        "thumbnails": {
          "default": {
            "url": "https://i.ytimg.com/vi/OIT9LpQKbeg/default.jpg",
            "width": 120,
            "height": 90
          },
          "medium": {
            "url": "https://i.ytimg.com/vi/OIT9LpQKbeg/mqdefault.jpg",
            "width": 320,
            "height": 180
          },
          "high": {
            "url": "https://i.ytimg.com/vi/OIT9LpQKbeg/hqdefault.jpg",
            "width": 480,
            "height": 360
          },
          "standard": {
            "url": "https://i.ytimg.com/vi/OIT9LpQKbeg/sddefault.jpg",
            "width": 640,
            "height": 480
          },
          "maxres": {
            "url": "https://i.ytimg.com/vi/OIT9LpQKbeg/maxresdefault.jpg",
            "width": 1280,
            "height": 720
          }
        },
        "channelTitle": "Synera",
        "playlistId": "PLzJ1mqwxogpFuFCk1YfUE1c0gWtnIutfz",
        "position": 6,
        "resourceId": {
          "kind": "youtube#video",
          "videoId": "OIT9LpQKbeg"
        },
        "videoOwnerChannelTitle": "あいみょん",
        "videoOwnerChannelId": "UCG8MvaPCa2ecKH3GZyFxduA"
      }
    },
    {
      "kind": "youtube#playlistItem",
      "etag": "swppFRUDAH4JBpS6Z9aa-MSq4Ew",
      "id": "UEx6SjFtcXd4b2dwRnVGQ2sxWWZVRTFjMGdXdG5JdXRmei40NzZCMERDMjVEN0RFRThB",
      "snippet": {
        "publishedAt": "2024-02-21T05:36:22Z",
        "channelId": "UCZtzcQ_fiXuw6dNx_AxK7_Q",
        "title": "YOASOBI「アイドル」 Official Music Video",
        "description": "Streaming & Download : https://orcd.co/yoasobi_idol\nMusic : Ayase (https://twitter.com/ayase_0404)\nVocal : ikura (https://twitter.com/ikutalilas)\n\nBackground Chorus English Lyrics：Konnie Aoki\nBackground Chorus：Ebony Bowens, Chloe Kibble, Marista Stubbs, Imani J. Dawson, Kyte, Lyle Carr, Andrew Soda\nBackground Shouts：REAL AKIBA BOYZ (https://www.youtube.com/@realakibaboyz )\n\n原作小説「45510」(赤坂アカ 著)\n4/12(水)24時30分同時公開\nhttps://youngjump.jp/oshinoko/novel_45510/\n\n○TVアニメ『【推しの子】』オープニング主題歌\n2023年4月12日(水)よりTVアニメ放送開始！\nhttps://ichigoproduction.com/\n\n＜INTRODUCTION＞ \n「この芸能界（せかい）において嘘は武器だ」\n地方都市で働く産婦人科医・ゴロー。\nある日\"推し\"のアイドル「B小町」のアイが彼の前に現れた。\n彼女はある禁断の秘密を抱えており…。\nそんな二人の\"最悪\"の出会いから、運命が動き出していく―。\n\n©赤坂アカ×横槍メンゴ／集英社・【推しの子】製作委員会\n\n○インスト音源はこちら\nhttps://piapro.jp/t/KQn0\n\n○YOASOBI初のアリーナツアー「YOASOBI ARENA TOUR 電光石火」追加公演決定！\n6月23日(金)・24日(土)＠神奈川県・ぴあアリーナMM\nhttps://www.yoasobi-music.jp/news/551184\n--\n無敵の笑顔で荒らすメディア\n知りたいその秘密ミステリアス\n抜けてるとこさえ彼女のエリア\n完璧で嘘つきな君は\n天才的なアイドル様\n\n今日何食べた？\n好きな本は？\n遊びに行くならどこに行くの？\n何も食べてない\nそれは内緒\n何を聞かれても\nのらりくらり\n\nそう淡々と\nだけど燦々と\n見えそうで見えない秘密は蜜の味\nあれもないないない\nこれもないないない\n好きなタイプは？\n相手は？\nさあ答えて\n\n「誰かを好きになることなんて\n私分からなくてさ」\n嘘か本当か知り得ない\nそんな言葉に\nまた一人堕ちる\nまた好きにさせる\n\n誰もが目を奪われていく\n君は完璧で究極のアイドル\n金輪際現れない\n一番星の生まれ変わり\nその笑顔で\n愛してるで\n誰も彼も虜にしていく\nその瞳が\nその言葉が\n嘘でもそれは\n完全なアイ\n\nはいはいあの子は特別です\n我々は端からおまけです\nお星様の引き立て役Bです\n全てがあの子のお陰な訳ない\nしゃらくさい\n妬み嫉妬なんてない訳がない\nこれはネタじゃない\nからこそ許せない\n完璧じゃない君じゃ許せない\n自分を許せない\n誰よりも強い君以外は認めない\n\n誰もが信じ崇めてる\nまさに最強で無敵のアイドル\n弱点なんて見当たらない\n一番星を宿している\n弱いとこなんて見せちゃ\nダメダメ\n知りたくないとこは見せずに\n唯一無二じゃなくちゃ\nイヤイヤ\nそれこそ本物のアイ\n\n得意の笑顔で沸かすメディア\n隠しきるこの秘密だけは\n愛してるって嘘で積むキャリア\nこれこそ私なりの愛だ\n\n流れる汗も綺麗なアクア\nルビーを隠したこの瞼\n歌い踊り舞う私はマリア\nそう嘘はとびきりの愛だ\n\n誰かに愛されたことも\n誰かのこと愛したこともない\nそんな私の嘘がいつか本当になること\n信じてる\n\nいつかきっと全部手に入れる\n私はそう欲張りなアイドル\n等身大でみんなのこと\nちゃんと愛したいから\n今日も嘘をつくの\nこの言葉が\nいつか本当になる日を願って\nそれでもまだ\n君と君にだけは言えずにいたけど\nやっと言えた\nこれは絶対嘘じゃない\n愛してる\n--\nMVディレクター・絵コンテ・演出：中山直哉\n編集：齊藤雄磨\nビジュアルデベロップメント・モーショングラフィックス：齊藤雄磨、山口駿\nロゴデザイン：lowpolydog\n作画監督：平山寛菜\n作画監督補佐：夘野智子、稲手遥香\n原画：菊地奨之、室賀彩花、山本ゆうすけ、尾辻浩晃、秦ほのか、引口奈緒子、北村由佳、水野公彰、中山薫、福家いおり、米村雅人、松井怜、夘野智子、卓子意、沢田犬二、辻彩夏、TOMATO\n動画工房作画部\n第二原画：動画工房作画部\n全後映、劉官林、中山薫、1110\n動画検査：大原真琴\n動画：大原真琴、小田道子、中山薫、米村雅人、松井怜\n寿門堂\nRadplus\n色彩設計：石黒けい\n色彩設計補佐：芦原明音\n色指定・仕上げ検査：伊藤裕香\n仕上げ：呉政宏、村田栞、真壁源太\n寿門堂\nRadplus\n撮影監督：桒野貴文\n撮影監督補佐：工藤康史\n撮影：福岡由惟、塩野修平\n美術監督：宇佐美哲也(スタジオイースター)\n美術設定：水本浩太(スタジオイースター)\n背景：スタジオイースター\n平田卓也、今井公平、廣川翔一、山口琴実、宇佐美哲也\n3DLO：渡辺悦啓、石橋涼介\nモニターワークス：前田大輔(レイ）\n制作プロデューサー：小林涼\n制作チーフ・制作進行：増田拓朗\n\nアニメーション制作 動画工房\n製作 【推しの子】製作委員会\n--\n#YOASOBI #アイドル #推しの子",
        "thumbnails": {
          "default": {
            "url": "https://i.ytimg.com/vi/ZRtdQ81jPUQ/default.jpg",
            "width": 120,
            "height": 90
          },
          "medium": {
            "url": "https://i.ytimg.com/vi/ZRtdQ81jPUQ/mqdefault.jpg",
            "width": 320,
            "height": 180
          },
          "high": {
            "url": "https://i.ytimg.com/vi/ZRtdQ81jPUQ/hqdefault.jpg",
            "width": 480,
            "height": 360
          },
          "standard": {
            "url": "https://i.ytimg.com/vi/ZRtdQ81jPUQ/sddefault.jpg",
            "width": 640,
            "height": 480
          },
          "maxres": {
            "url": "https://i.ytimg.com/vi/ZRtdQ81jPUQ/maxresdefault.jpg",
            "width": 1280,
            "height": 720
          }
        },
        "channelTitle": "Synera",
        "playlistId": "PLzJ1mqwxogpFuFCk1YfUE1c0gWtnIutfz",
        "position": 7,
        "resourceId": {
          "kind": "youtube#video",
          "videoId": "ZRtdQ81jPUQ"
        },
        "videoOwnerChannelTitle": "Ayase / YOASOBI",
        "videoOwnerChannelId": "UCvpredjG93ifbCP1Y77JyFA"
      }
    },
    {
      "kind": "youtube#playlistItem",
      "etag": "nRuqeh1UlH1TfM8wBlRdj6VKxTw",
      "id": "UEx6SjFtcXd4b2dwRnVGQ2sxWWZVRTFjMGdXdG5JdXRmei5EMEEwRUY5M0RDRTU3NDJC",
      "snippet": {
        "publishedAt": "2024-03-11T20:55:19Z",
        "channelId": "UCZtzcQ_fiXuw6dNx_AxK7_Q",
        "title": "YOASOBI「優しい彗星」Official Music Video　(YOASOBI - Comet)",
        "description": "Download＆Streaming配信中:https://orcd.co/comet\nTVアニメ『BEASTARS』第二期エンディングテーマ\n『BEASTARS』原作者・板垣巴瑠先生がこの楽曲の原作小説として書き下ろした「獅子座流星群のままに」はTVアニメBEASTARS公式HP[MUSIC]タブにて公開中！\nhttps://bst-anime.com/​\n--\n「優しい彗星 /  THE FIRST TAKE」\nhttps://youtu.be/EaA6NlH80wg\n--\nTVアニメ『BEASTARS』第二期オープニングテーマ「怪物」もぜひ合わせてお聴きください。\nhttps://youtu.be/dy90tA3TT1c\n--\nシングル『怪物/優しい彗星』好評発売中！\n-アニメ盤\nhttps://yoasobi.lnk.to/XSCL-54​\n\n-YOASOBIオフィシャルファンクラブ\"CLUB 夜遊\"限定盤\nhttps://yoasobi-fc.com/0303​\n--\n\n●YOASOBI：https://twitter.com/YOASOBI_staff​\nComposer : Ayase (https://twitter.com/ayase_0404​)\nVocal : ikura (https://twitter.com/ikutalilas​ )\n\n●MUSIC VIDEO\n-監督・制作\n門脇康平(https://twitter.com/kadowakikouhei)\n\n-アシスタント\n岡田直己\n小野颯志\n川村真優香\n北村徳郎\n木村かおる\n立川憲一朗\nまちだりな\n渡辺真有\n\n★インスト音源はこちら\nhttps://piapro.jp/t/Lm-C\n\n--\n今、静かな夜の中で\n無計画に車を走らせた\n左隣、あなたの\n横顔を月が照らした\n\nただ、思い出を探る様に\n辿る様に言葉を繋ぎ合わせれば\nどうしようもなく溢れてくる\n日々の記憶\n\nあなたのそばで生きると決めたその日から\n少しずつ変わり始めた世界\n強く在るように弱さを隠すように\n演じてきた日々に\nある日突然現れたその眼差しが\n知らなかったこと教えてくれた\n守るべきものがあればそれだけで\nこんなにも強くなれるんだ\n\n深い深い暗闇の中で\n出会い、共に過ごしてきた\n類の無い日々\n心地よかった\nいや、幸せだった\n確かにほら\n救われたんだよ\nあなたに\n\nわずかな光を捉えて輝いたのは\nまるで流れ星のような涙\n不器用な命から流れて零れ落ちた\n美しい涙\n\n強く大きな体に秘めた優しさも\nどこか苦しげなその顔も\n愛しく思うんだ\n姿形じゃないんだ\nやっと気付いたんだ\n無情に響く銃声が夜を引き裂く\n別れの息吹が襲いかかる\n刹那に輝いた無慈悲な流れ星\n祈りはただ届かずに消えた\n\nこの、手の中で燃え尽きた\n金色の優しい彗星を\n美しいたてがみを\n暗闇の中握り締めた\n--\n#優しい彗星​ #BEASTARS​ #YOASOBI​ #Comet #Ayase #ikura",
        "thumbnails": {
          "default": {
            "url": "https://i.ytimg.com/vi/VyvhvlYvRnc/default.jpg",
            "width": 120,
            "height": 90
          },
          "medium": {
            "url": "https://i.ytimg.com/vi/VyvhvlYvRnc/mqdefault.jpg",
            "width": 320,
            "height": 180
          },
          "high": {
            "url": "https://i.ytimg.com/vi/VyvhvlYvRnc/hqdefault.jpg",
            "width": 480,
            "height": 360
          },
          "standard": {
            "url": "https://i.ytimg.com/vi/VyvhvlYvRnc/sddefault.jpg",
            "width": 640,
            "height": 480
          },
          "maxres": {
            "url": "https://i.ytimg.com/vi/VyvhvlYvRnc/maxresdefault.jpg",
            "width": 1280,
            "height": 720
          }
        },
        "channelTitle": "Synera",
        "playlistId": "PLzJ1mqwxogpFuFCk1YfUE1c0gWtnIutfz",
        "position": 8,
        "resourceId": {
          "kind": "youtube#video",
          "videoId": "VyvhvlYvRnc"
        },
        "videoOwnerChannelTitle": "Ayase / YOASOBI",
        "videoOwnerChannelId": "UCvpredjG93ifbCP1Y77JyFA"
      }
    },
    {
      "kind": "youtube#playlistItem",
      "etag": "H6Cy4JSzXlL_J1g7lGKIDMddB6g",
      "id": "UEx6SjFtcXd4b2dwRnVGQ2sxWWZVRTFjMGdXdG5JdXRmei45ODRDNTg0QjA4NkFBNkQy",
      "snippet": {
        "publishedAt": "2024-03-20T08:19:13Z",
        "channelId": "UCZtzcQ_fiXuw6dNx_AxK7_Q",
        "title": "幾田りら「レンズ」Official Music Video",
        "description": "★TBS系 火曜ドラマ『持続可能な恋ですか？〜父と娘の結婚行進曲〜』主題歌\n\nストリーミング＆ダウンロード配信中！\nhttps://orcd.co/lens\n\n作詞・作曲：幾田りら　(Twitter：https://twitter.com/ikutalilas / Instagram：https://www.instagram.com/lilasikuta)\n編曲：KOHD \n\n〈comment〉\n■幾田りら■\nこの曲を書いている時、心に浮かべていた感情は、\n優しいものと苦しいもの、どちらも在りました。\n募るほどに閉じこもって冷えていく心と、\nただ想うだけで満たされ温まっていく心。\n二つが揺らめき合っているからこそ、\n愛するひとを大切に想うことができる瞬間もあるのではないでしょうか。\n\n志村監督との沢山のやりとりを経て、\nそんな二つの感情の間で揺れ動き、何かが変わっていく、ひとりの人の人生を\n共に描いていただけたと思います。\n\n\n■監督:志村知晴■\n2022. TOKYO ”Ikuta Lilas” ついに降臨\n\n立ち会えたことがまずとても光栄です。ありがとうございます。\n当初曲の世界を膨らませるには、と、実は演出を色々考えました。\nしかし、初mv。そして、りらさんの歌う姿が1番のびのびしている姿に寄り添って一緒に旅することが一番まっすぐな気がする。\nと思い、一つドレスを纏い、街を奔放に歌い、踊ったり、自由に曲を喜んで表現する姿と同時に曲中の詩の物語に想いを馳せりらさんと一緒に描きました。\n\nりらさんは優しくてしなやかな中に鋭く強い出で立ちと声をお持ちの方で、\nその上とても踊りの力をお持ちで、オーダーもあったこともあり、振付を多用しようと当初は考え作っていたのですが、\nお話しさせて頂く内、歌を大切に気持ちと繋げていらっしゃる姿もみえ、形の強い振りははじき、\n”この振付はどういう気持ちで体を回しているのか”、”なんで手をつけるのか”など気持ちと理由のある動きに向きを変え、\n踊りに緊張しないよう、りらさんのお守りになるような動きをと考え、一つ一つ話しながらお伝えしました。\n\n長い撮影の中、凛と表現されている姿には圧巻で、一つ一つ一緒にお話しして探り、屋上まで撮り進めた先で単色ではない力強い表現を発していらして、とてもカッコ良かったです。\n\n\n■スタイリスト:藤本大輔■\n今回の衣装は\n「幾田りらの頭の中、夢、願い」を具現化したいと考え【非日常】をテーマとし、着ることよりも在ることを元に選びました。\n\nジャケットのほとんどをフューシャピンクのフリルで覆われたロングドレスは、それだけで日常の風景を一変する力があります。\n\nあえてアクセサリーは一切付けず、トップスもパンツもレザーアイテムで揃え、意志の強い女性像を打ち出し、その女性が纏うことで\n“レンズ”が持つ世界観を多角的に表現しました。\n\n\n■ヘアメイク:YOUCA■\n今回のMVではいつもより大人っぽいメイクをしているのですが、同時に ありのままの彼女 という部分も表現したかったので、あえてリップやネイルは引き算をして作り込まないナチュラルな部分を出しています。彼女の繊細な表情や動きが交わり、 新しい姿 を見れたように思います。\n\n\n・・・\n一人歩く\n帰り道の途中\nイヤホンから伝うこの歌は\n二人だけの\n夕映えに貴方が\n教えてくれた小さな幸せ\n\n見返す写真には少し見切れた\n後ろ姿の貴方が写っている\n\nかざしたレンズのその先に\nただ貴方がそこにいれば\n華やいでいく心がここにあって\n未だに私を離さない\n\n一人きりの\nまだ少し冷えるベッドで\n何度も寝返りを打つ\n二人はいつ\n同じだけの想い\n一つの写真に重ねれるの？\n\n隣にいれば温かい心も\n夜が来る度 また冷めていくの\n\n私の瞳もいつからか\nただ一人貴方だけに\nどんなに遠く小さく片隅でも\nピントを合わせてしまう\n\nだらしなく揺れる背中さえも\n振り向いてみせる笑顔も\n一つも溢さずに焼き付けていたいよ\n\nかざしたレンズの真ん中に\nただ貴方を映していたい\nおぼつかない手つきでも精一杯\nその姿を捉えて\n\n貴方が瞳の真ん中に\n映すのは誰なのかな？\nいつか二人寄り添い笑う日々が\nアルバムを彩れるように\n・・・\n\n〈Music Video Staff〉\nDirector / Choreographer : Chiharu Shimura\n\nDirector of Photography : Keisuke Imamura\nLighting Director : Motoki Tanabe\nGrip Operator : Toshiyuki Ichihara (SCREW)\nProduction Designer : Chihiro Matsumoto / Minami Sakurai (R.mond)\n\nStylist : Daisuke Fujimoto\nHair & Make : YOUCA\nCar : nova_chan62\n\nTransport : Junichiro Ikuta\nColorist : Masahiro Ishiyama (ARTONE FILM)\nOnline Editor : Yohei Hirooka / Wataru Tamezawa (L’espace Vision)\nProduction Manager : Ken Inoue\nProducer : Takashi Sugai (CROMANYON)\nProduction : CROMANYON",
        "thumbnails": {
          "default": {
            "url": "https://i.ytimg.com/vi/tGj-dXAX590/default.jpg",
            "width": 120,
            "height": 90
          },
          "medium": {
            "url": "https://i.ytimg.com/vi/tGj-dXAX590/mqdefault.jpg",
            "width": 320,
            "height": 180
          },
          "high": {
            "url": "https://i.ytimg.com/vi/tGj-dXAX590/hqdefault.jpg",
            "width": 480,
            "height": 360
          },
          "standard": {
            "url": "https://i.ytimg.com/vi/tGj-dXAX590/sddefault.jpg",
            "width": 640,
            "height": 480
          },
          "maxres": {
            "url": "https://i.ytimg.com/vi/tGj-dXAX590/maxresdefault.jpg",
            "width": 1280,
            "height": 720
          }
        },
        "channelTitle": "Synera",
        "playlistId": "PLzJ1mqwxogpFuFCk1YfUE1c0gWtnIutfz",
        "position": 9,
        "resourceId": {
          "kind": "youtube#video",
          "videoId": "tGj-dXAX590"
        },
        "videoOwnerChannelTitle": "幾田りら Official",
        "videoOwnerChannelId": "UCztEY6czNyJKjRWMwuur9bg"
      }
    },
    {
      "kind": "youtube#playlistItem",
      "etag": "l7jYIRYgDyYqIbCsy3fbydkW9jk",
      "id": "UEx6SjFtcXd4b2dwRnVGQ2sxWWZVRTFjMGdXdG5JdXRmei4zMDg5MkQ5MEVDMEM1NTg2",
      "snippet": {
        "publishedAt": "2024-03-20T08:19:29Z",
        "channelId": "UCZtzcQ_fiXuw6dNx_AxK7_Q",
        "title": "幾田りら「スパークル」Official Music Video",
        "description": "ストリーミング＆ダウンロード配信中！\nhttps://orcd.co/lilas_sparkle\n\n★ABEMA『今日、好きになりました。蜜柑編』主題歌、ABEMA『今日、好きになりました。卒業編2022』主題歌\n\n作詞・作曲：幾田りら　(Twitter：https://twitter.com/ikutalilas / Instagram：https://www.instagram.com/lilasikuta)\n編曲：中野領太\n\n◆幾田りら コメント\nこの楽曲は片思いの恋愛がテーマでありながら、恋をすることで色んな旅をしてきた人の成長を歌った曲です。\n片思いは切なく、儚いけれど、その愛しさも苦しさもすべてが宝物のように煌めき、旅立つ背中をそっと押してくれて、前に進んでいく。そんな一人の人間の成長を見届けるようなストーリーに山口監督がしてくださったので、このミュージックビデオをもって楽曲が完成したと思います。皆さんの大切な思い出も重ね合わせながら見てもらえたら嬉しいです。\n\n◆MV監督・山口祐果 コメント\n一瞬の煌めきから始まる“スパークル”は\n夢を見続け、傷つきながらも最終的に恋をした意味をしっかり見つける物語です。\n私は楽曲を聴きながら、「実らない恋に終わりを告げたその人は、流れ星のような一瞬の経験をしたことで一歩大人になり\n新しい道を進み続けていくのだろうな〜」など想像していると“旅たちの日”の情景が頭に浮かんできました。\n次の人生に進むにあたって、たくさんの思い出が詰まった場所を離れる時\nその人はそこで起きた一瞬の“煌めき達をしっかり思い出し、消化し、旅立っていきます。\n幾田りらさんのスパークルは複雑な片思いの心境を整理したかのように、\n素直で真っ直ぐな言葉で歌われているのが印象的でしたので映像もなるべくシンプルで真っ直ぐな印象になるように心掛けました。\n\nこの作品に最高なスタッフと一緒に携われてとても光栄でした。\nありがとうございました！\n\n・・・\n煌めいて消えてった\nひとひらの恋の結末は\n\n落っこちてくような\n心地がしたのは\n目と目が合った時でした\nほんの一瞬のこと\n\nきっと困らせちゃうでしょ？\n全部伝えてしまえば\n崩れていくものばかりが\n頭をめぐるめぐる\n\n君が愛おしく思うのは私じゃないかもと\nどこかでずっと感じているのに\nのぼせた頬を夜風に任せて\n冷やして\n\n煌めいて消えてった\nひとひらの恋の結末は\n痛いほど始めから決まっていたんだ\nそれでも君の横顔 愛おしくなって\n浮かんだ二文字が駆けめぐる\n声に出来ず\n\nこんな近くにいるのに\nいつも遠くを見ているね\n本当の君が知りたいの\nなんて言えるわけないけど\n\n柔らかい声 あどけない仕草 \n君に夢中になって\n周りがもっと見えなくなっていく\nまだ側にいたいって\n言えるような距離になれたら\n\n煌めいて消えてった\n夜空を走り去る星のように\nひとときの幸せ 逃さないように\n瞬きも惜しいほど君をみていた\nきっといつかどこかへ\n行くのでしょう？\n\nいつだって止められるはずの恋に\n夢を見続けては\n覚めないでと願ってしまう\n曖昧も怖いも握り締めて\n\n君が好き それだけが\n嘘のない私の気持ちで\n痛くても分かっていても\n変わりはしないんだ\n苦しさも愛しさも\n全部君から貰えて良かった\n忘れないよ日々を\n恋をした意味を\n\n落っこちていくような\n心地がしたのは\n目と目が合った時でした\nほんの一瞬のこと\n・・・\n\n〈Music Video Staff〉\nDirector\n山口 祐果\n\nChinematographer\n寺村 周歩\n\nCamera Assistant\n大友 大輝\n大池 雅\n柴田 悠斗\n\nLighting Director\n原澤 遥哉\n\nLighting Assistant\n徳弘 大知\n中島 拓巳\n深本 真鈴\n\nStyling\n藤本 大輔\n\nHair&Make-Up\nYOUCA\n\nColorrist\n有賀 遼(ARTONE FILM)\n\nOnline Editor\n福井 優太\n杉野智哉\n\nVFX Editor\nNANON\n\nVFX Producer\n菅井 慧太\n\nVFX Manager\n渡辺 大智\n\nDriver\n岸根 明\n\nLocation Driver \nBONDS \n\nProduction Manager\n白澤 優\n岡部 明日実\n\nProducer\n武居 航暉 / 井本 翔\n\nProduction Company\nPROJECT K",
        "thumbnails": {
          "default": {
            "url": "https://i.ytimg.com/vi/q4CbHfW3Ji8/default.jpg",
            "width": 120,
            "height": 90
          },
          "medium": {
            "url": "https://i.ytimg.com/vi/q4CbHfW3Ji8/mqdefault.jpg",
            "width": 320,
            "height": 180
          },
          "high": {
            "url": "https://i.ytimg.com/vi/q4CbHfW3Ji8/hqdefault.jpg",
            "width": 480,
            "height": 360
          },
          "standard": {
            "url": "https://i.ytimg.com/vi/q4CbHfW3Ji8/sddefault.jpg",
            "width": 640,
            "height": 480
          },
          "maxres": {
            "url": "https://i.ytimg.com/vi/q4CbHfW3Ji8/maxresdefault.jpg",
            "width": 1280,
            "height": 720
          }
        },
        "channelTitle": "Synera",
        "playlistId": "PLzJ1mqwxogpFuFCk1YfUE1c0gWtnIutfz",
        "position": 10,
        "resourceId": {
          "kind": "youtube#video",
          "videoId": "q4CbHfW3Ji8"
        },
        "videoOwnerChannelTitle": "幾田りら Official",
        "videoOwnerChannelId": "UCztEY6czNyJKjRWMwuur9bg"
      }
    },
    {
      "kind": "youtube#playlistItem",
      "etag": "Y9TmGH7kXN8jHBSrMU9vZuzp_2A",
      "id": "UEx6SjFtcXd4b2dwRnVGQ2sxWWZVRTFjMGdXdG5JdXRmei41Mzk2QTAxMTkzNDk4MDhF",
      "snippet": {
        "publishedAt": "2024-03-20T08:20:02Z",
        "channelId": "UCZtzcQ_fiXuw6dNx_AxK7_Q",
        "title": "明日への扉 / I WiSH（川嶋あい）(Covered by コバソロ & こぴ)",
        "description": "今回はあいのり主題歌、 I WiSHの明日への扉をカバーしました。今回のボーカルはこぴさん！チャンネル登録してね！▶︎ https://www.youtube.com/user/Hujikoman\n\n【こぴ】\nTwitter▶︎ https://twitter.com/kopichan_\nInstagram▶︎ https://www.instagram.com/kopiyama_/\nYouTube▶︎ https://www.youtube.com/channel/UCW03mhXZjtlqE8P_bewxl6g\n\n【RELEASE INFORMATION】\n⚫︎⚫︎⚫︎⚫︎⚫︎Original⚫︎⚫︎⚫︎⚫︎⚫︎\n\n★2019.3.26 Release!!\n配信限定2nd album「Clumsy」\n1500円\n配信サイト一覧→https://linkco.re/prxtScat\n収録曲\nM1 どうか幸せにならないで feat. 春茶\nM2 新世界のユーツ feat. SiN\nM3 会いたくて feat. こぴ\nM4 夏恋慕 feat. 春茶\nM5 春に揺られど君想う feat. こぴ\nM6 ラブレター feat. 春茶\nM7 言葉さがし feat. こぴ & SiN\nM8 outro\n\n★1st full album「KOBASOLO」\n配信サイト一覧→ https://linkco.re/cy6VH9VX\nCD通販→ https://kobasolo.stores.jp\n\n⚫︎⚫︎⚫︎⚫︎⚫︎Cover⚫︎⚫︎⚫︎⚫︎⚫︎\n\n★2nd Cover Album「これくしょん２」NEW!!\n配信サイト一覧→ https://vap.lnk.to/collection2\nAmazon→ https://www.amazon.co.jp/dp/B07KZ1Y2Q5/ref=cm_sw_r_tw_dp_U_x_Dd1FCbA45JPNM\n全国CDショップやAmazon、楽天などでも発売中!!\n\n★1st Cover Album「これくしょん」\n配信サイト一覧→ https://vap.lnk.to/correction\nAmazon→ https://www.amazon.co.jp/dp/B073WSPGM5/ref=cm_sw_r_tw_dp_U_x_Se1FCbV3TWWHN\n全国CDショップやAmazon、楽天などでも発売中!!\n\n★コバソロ & 未来 \n配信限定EP「MIRAI COVERS」\n配信サイト一覧→ https://umj.lnk.to/zxNBB\n\n★Cover Album「これくしょん」特設サイトhttp://www.vap.co.jp/kobasolo/\n\n⚫︎⚫︎⚫︎⚫︎⚫︎⚫︎⚫︎⚫︎⚫︎⚫︎⚫︎⚫︎⚫︎⚫︎⚫︎⚫︎⚫︎⚫︎⚫︎⚫︎⚫︎⚫︎⚫︎⚫︎⚫︎⚫︎⚫︎⚫︎⚫︎⚫︎⚫︎⚫︎⚫︎⚫︎⚫︎\n\n【コバソロ/Kobasolo】\nYouTube▶︎http://www.youtube.com/user/Hujikoman\n2ndチャンネル▶︎https://goo.gl/FuH0aR\nTwitter▶︎https://twitter.com/kobamakolts\nfacebook▶︎http://www.facebook.com/#!/kobasolo\ninstagram▶︎http://instagram.com/kobasolo/\nHP▶︎http://kobasolo.net/\nオンラインショップ▶︎https://kobasolo.stores.jp\n\n【オリジナル曲MV】\n★エンディング曲\n『君さえいなけりゃ feat. 春茶/コバソロ』\niTunes▶︎https://apple.co/2jMiMvi\nMV▶︎https://youtu.be/-KOeQapXsx8\n\n【使用機材】───────────────\n●カメラ(2012〜2016)https://amzn.to/2U54NEF\n● カメラ(2017〜)https://amzn.to/2Wf6v3F\nhttps://amzn.to/2JqOw8T\n\n●レンズ\nhttps://amzn.to/2WdXqYN\nhttps://amzn.to/2Jrs7Ik\nhttps://amzn.to/2HL91dN\n\n●スタビライザー\nhttps://amzn.to/2FoeUfs\nhttps://amzn.to/2Wdf9zC\n\n●照明\nhttps://amzn.to/2HJ6IYK\nhttps://amzn.to/2WdIxWb\n\n●DTMソフト\nhttps://amzn.to/2TNEcwd\n\n●ヘッドホン\nhttps://amzn.to/2Fo5CAc\n\n●オーディオインターフェース\nhttps://amzn.to/2FpX7ok\n\n●コンデンサーマイク\nhttps://amzn.to/2TWRKVp\nhttps://amzn.to/2W6vc1S\n\n※上記製品リンクURLはAmazonアソシエイトのリンクを使用しています。\n\n\n■─────────────────────────────────■\nThis video is\nFilmed by kobasolo\nEdited by kobasolo\nAudio produced by kobasolo",
        "thumbnails": {
          "default": {
            "url": "https://i.ytimg.com/vi/z94ur-O6JJk/default.jpg",
            "width": 120,
            "height": 90
          },
          "medium": {
            "url": "https://i.ytimg.com/vi/z94ur-O6JJk/mqdefault.jpg",
            "width": 320,
            "height": 180
          },
          "high": {
            "url": "https://i.ytimg.com/vi/z94ur-O6JJk/hqdefault.jpg",
            "width": 480,
            "height": 360
          },
          "standard": {
            "url": "https://i.ytimg.com/vi/z94ur-O6JJk/sddefault.jpg",
            "width": 640,
            "height": 480
          },
          "maxres": {
            "url": "https://i.ytimg.com/vi/z94ur-O6JJk/maxresdefault.jpg",
            "width": 1280,
            "height": 720
          }
        },
        "channelTitle": "Synera",
        "playlistId": "PLzJ1mqwxogpFuFCk1YfUE1c0gWtnIutfz",
        "position": 11,
        "resourceId": {
          "kind": "youtube#video",
          "videoId": "z94ur-O6JJk"
        },
        "videoOwnerChannelTitle": "kobasolo",
        "videoOwnerChannelId": "UCDbQblY1XASbgqOXmy6FOFQ"
      }
    },
    {
      "kind": "youtube#playlistItem",
      "etag": "NCBCvZgkD4xWvxa8WMIqMcicI2A",
      "id": "UEx6SjFtcXd4b2dwRnVGQ2sxWWZVRTFjMGdXdG5JdXRmei5EQUE1NTFDRjcwMDg0NEMz",
      "snippet": {
        "publishedAt": "2024-03-20T08:20:24Z",
        "channelId": "UCZtzcQ_fiXuw6dNx_AxK7_Q",
        "title": "西野カナ Kana Nishino 『トリセツ』 (LOVE it Tour ~10th Anniversary~)",
        "description": "LOVE it Tour ~10th Anniversary~\n2018.10.9 & 10.10 at 横浜アリーナ Yokohama Arena",
        "thumbnails": {
          "default": {
            "url": "https://i.ytimg.com/vi/1IULa5b6IkI/default.jpg",
            "width": 120,
            "height": 90
          },
          "medium": {
            "url": "https://i.ytimg.com/vi/1IULa5b6IkI/mqdefault.jpg",
            "width": 320,
            "height": 180
          },
          "high": {
            "url": "https://i.ytimg.com/vi/1IULa5b6IkI/hqdefault.jpg",
            "width": 480,
            "height": 360
          },
          "standard": {
            "url": "https://i.ytimg.com/vi/1IULa5b6IkI/sddefault.jpg",
            "width": 640,
            "height": 480
          }
        },
        "channelTitle": "Synera",
        "playlistId": "PLzJ1mqwxogpFuFCk1YfUE1c0gWtnIutfz",
        "position": 12,
        "resourceId": {
          "kind": "youtube#video",
          "videoId": "1IULa5b6IkI"
        },
        "videoOwnerChannelTitle": "坪田玉織",
        "videoOwnerChannelId": "UCS7kex3CGDgzdK8VANeog4Q"
      }
    },
    {
      "kind": "youtube#playlistItem",
      "etag": "6z1DKDZxjz4A9HN9UW3PmRPqRfA",
      "id": "UEx6SjFtcXd4b2dwRnVGQ2sxWWZVRTFjMGdXdG5JdXRmei41QTY1Q0UxMTVCODczNThE",
      "snippet": {
        "publishedAt": "2024-03-20T08:21:05Z",
        "channelId": "UCZtzcQ_fiXuw6dNx_AxK7_Q",
        "title": "Novelbright - ツキミソウ [Official Music Video]",
        "description": "2020.12.11 Release\nStreaming&DL▶️ https://Novelbright.lnk.to/OpeningDeclaration\n各種音楽配信&サブスクリプションサービスで配信中！\n\n「ツキミソウ」Official Live Video at Zepp Tokyo\nhttps://youtu.be/Koeglo3-MBI\n\n「THE FIRST TAKE」\nストリングスとピアノだけのアレンジで披露！\nhttps://youtu.be/yqFNDgsxudo\n\nツキミソウinst音源（BPM 78）\nhttps://piapro.jp/t/PpcS\n\n----------------------------------------------------------------------------------------------\n2022.5.18 Release\nMajor 2nd Full Album「Assort」\n予約受付中▶https://novelbright.lnk.to/Assort_Reserve\n----------------------------------------------------------------------------------------------\n2024年4月6日(土)北海道公演から始まる全国ワンマンツアー\n「Novelbright LIVE TOUR 2024 ～CIRCUS～」開催！\n多くの公演がSOLD OUT！4/12(金)山口公演のみチケットあります\n\n■各プレイガイド一般発売中！\n受付期間：2月3日(土)10:00～\n【チケット】\n全席指定      　　 　  :￥7,000(税込)\n全席指定【学割】　　　 :￥4,900（税込）\n\nチケットぴあ：https://w.pia.jp/t/novelbright/\nイープラス：https://eplus.jp/novelbright/\nローソンチケット：https://l-tike.com/novelbright/\n\n●5/22(水)東京・8/5(月)北海道追加公演のFC2次抽選先行が4/2(火)18時より開始！\n詳細はHPご覧ください\n受付期間：4/2(火)18:00～4/7(日)23:59\nhttps://novelbright.jp/news/detail/1790\n\n4月6日(土)　 【北海道】 カナモトホール\n4月12日(金)  【山口県】KDDI維新ホール メインホール\n4月14日(日)  【広島県】呉信用金庫ホール(呉市文化ホール)\n4月19日(金)  【香川県】サンポートホール高松 大ホール\n4月20日(土)  【愛媛県】松山市民会館 大ホール\n4月27日(土)  【群馬県】高崎芸術劇場 大劇場\n4月29日(月祝)【栃木県】栃木県総合文化センター メインホール\n5月2日(木)   【愛知県】名古屋国際会議場センチュリーホール\n5月10日(金)  【福井県】鯖江市文化センター\n5月17日(金)  【福島県】白河文化交流館コミネス 大ホール\n5月22日(水)　【東京都】Zepp DiverCity(TOKYO) ※追加公演\n5月24日(金)  【福岡県】福岡市民会館\n5月26日(日)  【京都府】文化パルク城陽 プラムホール\n6月1日(土) 　【岡山県】岡山芸術創造劇場ハレノワ 大劇場\n6月2日(日) 　【島根県】出雲市民会館 大ホール\n6月6日(木) 　【大阪府】オリックス劇場\n6月8日(土) 　【静岡県】静岡市民文化会館 中ホール\n6月15日(土)  【宮崎県】都城市総合文化ホール 大ホール\n6月16日(日)  【佐賀県】鳥栖市民文化会館\n6月21日(金)  【石川県】本多の森 北電ホール\n6月23日(日)  【岐阜県】岐阜市民会館 大ホール\n6月28日(金)  【奈良県】なら100年会館 大ホール\n6月30日(日)  【滋賀県】守山市民ホール 大ホール\n7月6日(土) 　【山形県】酒田市民会館(希望ホール) 大ホール\n7月7日(日) 　【宮城県】トークネットホール仙台(仙台市民会館)\n7月26日(金)  【東京都】東京ガーデンシアター\n8月5日(月)　 【北海道】カナモトホール ※追加公演\n----------------------------------------------------------------------------------------------\nCast：Yumi Wakatsuki / Minehiro Kinomoto\nDirector/Cinemato Grapher/Editor：ill.pics\n1st Assistant Camera：Kenichi Yamada\n2nd Assistant Camera：Riku Matsuse\nHairmake ：Natsuki\nHairmake (Yumi Wakatsuki)：Mami Numata（ilumini.）\nStylist ：Yui Kuranoshita\nAssistant Stylist：Hana Kaneda\nProducer：Ayano Tsushima\nAissistant Producer：Yukiko Yamamoto\nProduction Manager：Akiko Tachikawa\nProduction：UNITED PRODUCTIONS\nBrand：ATSUSHI NAKASHIMA/417 EDIFICE/FREAK'S STORE\n----------------------------------------------------------------------------------------------\n\n[OFFICIAL HP]\nhttps://novelbright.jp/\n\n[OFFICIAL Twitter]\nhttps://twitter.com/Novelbright_jp\nID : @Novelbright_jp\n\nNovelbright [ノーベルブライト]\nVo.竹中雄大の心を震わす圧倒的な歌声、一度聴いたら忘れられない確かなメロディワーク、\n細部まで練りこまれた楽曲アレンジに定評がある、大阪発5人組ロックバンド。\n\n#Novelbright #ツキミソウ #若月佑美",
        "thumbnails": {
          "default": {
            "url": "https://i.ytimg.com/vi/WAMxwRtNrPY/default.jpg",
            "width": 120,
            "height": 90
          },
          "medium": {
            "url": "https://i.ytimg.com/vi/WAMxwRtNrPY/mqdefault.jpg",
            "width": 320,
            "height": 180
          },
          "high": {
            "url": "https://i.ytimg.com/vi/WAMxwRtNrPY/hqdefault.jpg",
            "width": 480,
            "height": 360
          },
          "standard": {
            "url": "https://i.ytimg.com/vi/WAMxwRtNrPY/sddefault.jpg",
            "width": 640,
            "height": 480
          },
          "maxres": {
            "url": "https://i.ytimg.com/vi/WAMxwRtNrPY/maxresdefault.jpg",
            "width": 1280,
            "height": 720
          }
        },
        "channelTitle": "Synera",
        "playlistId": "PLzJ1mqwxogpFuFCk1YfUE1c0gWtnIutfz",
        "position": 13,
        "resourceId": {
          "kind": "youtube#video",
          "videoId": "WAMxwRtNrPY"
        },
        "videoOwnerChannelTitle": "Novelbright",
        "videoOwnerChannelId": "UCIJAlAYCNN8RACtDDsy9K6g"
      }
    },
    {
      "kind": "youtube#playlistItem",
      "etag": "HNhqbkYMhSATLjG_kvHuWtzTu1c",
      "id": "UEx6SjFtcXd4b2dwRnVGQ2sxWWZVRTFjMGdXdG5JdXRmei4yMUQyQTQzMjRDNzMyQTMy",
      "snippet": {
        "publishedAt": "2024-03-20T08:21:41Z",
        "channelId": "UCZtzcQ_fiXuw6dNx_AxK7_Q",
        "title": "【Ado】ギラギラ",
        "description": "もしも神様が左利きならどんなに幸せか知れない\n\nダウンロード/ストリーミング配信はこちら：https://ado.lnk.to/giragiraID\n\n↓inst音源↓\nhttps://piapro.jp/t/6BVH\n\nVo：Ado \nhttps://twitter.com/ado1024imokenp \n\nMusic & Lyrics：てにをは様 \nhttps://twitter.com/edogawa_sampo\n\nMix：Naoki Itai 様\nhttps://twitter.com/NaokI_Edge \n\nMovie：沼田ゾンビ様\nhttps://twitter.com/Dobuu_2\n\nImage Director：ORIHARA様 \nhttps://twitter.com/ewkkyorhr \n\n----------------------------------- \n■2022.1.26 Release\n1st Album『狂言』発売/配信中\nhttps://ado.lnk.to/kyogenID\n\n■1st Album『狂言』特設サイト\nhttps://sp.universal-music.co.jp/ado/kyogen/\n ----------------------------------- \nURL \n・Twitter: https://twitter.com/ado1024imokenp\n・YouTube: https://www.youtube.com/c/Ado1024\n・ユニバーサルミュージック公式ページ:　 https://www.universal-music.co.jp/ado/ \n・プロフィール:　 https://cloud9pro.co.jp/artist/profile/ado/ \n----------------------------------- \n\n#Ado #ギラギラ",
        "thumbnails": {
          "default": {
            "url": "https://i.ytimg.com/vi/sOiMD45QGLs/default.jpg",
            "width": 120,
            "height": 90
          },
          "medium": {
            "url": "https://i.ytimg.com/vi/sOiMD45QGLs/mqdefault.jpg",
            "width": 320,
            "height": 180
          },
          "high": {
            "url": "https://i.ytimg.com/vi/sOiMD45QGLs/hqdefault.jpg",
            "width": 480,
            "height": 360
          },
          "standard": {
            "url": "https://i.ytimg.com/vi/sOiMD45QGLs/sddefault.jpg",
            "width": 640,
            "height": 480
          },
          "maxres": {
            "url": "https://i.ytimg.com/vi/sOiMD45QGLs/maxresdefault.jpg",
            "width": 1280,
            "height": 720
          }
        },
        "channelTitle": "Synera",
        "playlistId": "PLzJ1mqwxogpFuFCk1YfUE1c0gWtnIutfz",
        "position": 14,
        "resourceId": {
          "kind": "youtube#video",
          "videoId": "sOiMD45QGLs"
        },
        "videoOwnerChannelTitle": "Ado",
        "videoOwnerChannelId": "UCln9P4Qm3-EAY4aiEPmRwEA"
      }
    },
    {
      "kind": "youtube#playlistItem",
      "etag": "oPeq64LaGfKQ_zj6FWShFWP1zio",
      "id": "UEx6SjFtcXd4b2dwRnVGQ2sxWWZVRTFjMGdXdG5JdXRmei45RTgxNDRBMzUwRjQ0MDhC",
      "snippet": {
        "publishedAt": "2024-03-20T08:21:47Z",
        "channelId": "UCZtzcQ_fiXuw6dNx_AxK7_Q",
        "title": "【Ado】踊",
        "description": "ﾉヽ･/ ﾉヽ° 👾ﾅょら ⓚⓞーー💥🤟💙 🌴👽笑笑 \n\nStreaming & Downloadはこちら：\nhttps://ado.lnk.to/odoID \n\n↓inst音源↓\nhttps://piapro.jp/t/TDE9\n\nVo：Ado\nhttps://twitter.com/ado1024imokenp \n\nMusic & Arrange & Mix：Giga様 \nhttps://twitter.com/GigaMozuku\n\nMusic & Arrange：TeddyLoid様\nhttps://twitter.com/TeddyLoidSpace\n\nLyrics：DECO*27様\nhttps://twitter.com/DECO27\n\nIllust：かゆか様\nhttps://twitter.com/17_s_kyk \n\nMovie：藍瀬 まなみ様\nhttps://twitter.com/AiseManami \n\nImage Director：ORIHARA様 \nhttps://twitter.com/ewkkyorhr \n\nNHK総合「夜光音楽 ボカロP 5min.」テーマソング\nhttps://www.nhk.or.jp/music/programs/447912.html\n\n----------------------------------- \n■2022.1.26 Release\n1st Album『狂言』発売/配信中\nhttps://ado.lnk.to/kyogenID\n\n■1st Album『狂言』特設サイト\nhttps://sp.universal-music.co.jp/ado/kyogen/\n----------------------------------- \nURL \n・Twitter: https://twitter.com/ado1024imokenp \n・YouTube: https://www.youtube.com/c/Ado1024\n・TikTok: https://www.tiktok.com/@ado1024osenbei? \n・ユニバーサルミュージック公式ページ:　 https://www.universal-music.co.jp/ado/ \n・プロフィール:　 https://cloud9pro.co.jp/artist/profile/ado/ \n----------------------------------- \n#Ado #踊",
        "thumbnails": {
          "default": {
            "url": "https://i.ytimg.com/vi/YnSW8ian29w/default.jpg",
            "width": 120,
            "height": 90
          },
          "medium": {
            "url": "https://i.ytimg.com/vi/YnSW8ian29w/mqdefault.jpg",
            "width": 320,
            "height": 180
          },
          "high": {
            "url": "https://i.ytimg.com/vi/YnSW8ian29w/hqdefault.jpg",
            "width": 480,
            "height": 360
          },
          "standard": {
            "url": "https://i.ytimg.com/vi/YnSW8ian29w/sddefault.jpg",
            "width": 640,
            "height": 480
          },
          "maxres": {
            "url": "https://i.ytimg.com/vi/YnSW8ian29w/maxresdefault.jpg",
            "width": 1280,
            "height": 720
          }
        },
        "channelTitle": "Synera",
        "playlistId": "PLzJ1mqwxogpFuFCk1YfUE1c0gWtnIutfz",
        "position": 15,
        "resourceId": {
          "kind": "youtube#video",
          "videoId": "YnSW8ian29w"
        },
        "videoOwnerChannelTitle": "Ado",
        "videoOwnerChannelId": "UCln9P4Qm3-EAY4aiEPmRwEA"
      }
    },
    {
      "kind": "youtube#playlistItem",
      "etag": "Xyl1zAtE4l2m_srpvHv-ueUtlCY",
      "id": "UEx6SjFtcXd4b2dwRnVGQ2sxWWZVRTFjMGdXdG5JdXRmei5ENDU4Q0M4RDExNzM1Mjcy",
      "snippet": {
        "publishedAt": "2024-03-20T08:21:56Z",
        "channelId": "UCZtzcQ_fiXuw6dNx_AxK7_Q",
        "title": "DAOKO × 米津玄師『打上花火』MUSIC VIDEO",
        "description": "DAOKO × 米津玄師『打上花火』MUSIC VIDEO\n──────\n▶NEW Single：Daoko「天使がいたよ 」＞https://linkco.re/1vBXaGDs\n▶NEXT Daoko LIVE  ＞https://daoko.jp/live/\n──────\nDAOKO × 米津玄師『打上花火』配信中！\n▽iTunes\nhttps://itunes.apple.com/jp/album/id1263790414?l=ja&ls=1&app=itunes\n\nDAOKO × 米津玄師『打上花火』アニメーションMUSIC VIDEO\n映画『打ち上げ花火、下から見るか？横から見るか？』主題歌\n　\n\nDAOKO  3rdシングル「打上花火」\n2017年8月16日（水）発売\n\n初回限定盤［CD+DVD］TFCC-89631　¥1,620（税込）\n　イラスト描き下ろしジャケット\n　DAOKO 2016 ”青色主義” TOUR at 赤坂BLITZ 2016.09.22 ライブ映像収録\n通常盤［CD］TFCC-89632　¥1,296（税込）\n\n＜収録曲＞\n映画『打ち上げ花火、下から見るか？横から見るか？』主題歌\n01. 打上花火／DAOKO × 米津玄師\n　作詞・作曲：米津玄師\n　Produced by 米津玄師\n\n映画『打ち上げ花火、下から見るか？横から見るか？』挿入歌\n02. Forever Friends／DAOKO\n　作詞・作曲：REMEDIOS　\n\n※通常盤のみの収録　『神撃のバハムートVIRGIN SOUL』エンディングテーマ\n3. Cinderella step／DAOKO\n　作詞・作曲　DAOKO　編曲　江島啓一（サカナクション）\n\n\n＜映画『打ち上げ花火、下から見るか？横から見るか？』情報＞\n\n声の出演：広瀬すず　菅田将暉\n　　　宮野真守 ／ 浅沼晋太郎　豊永利行　梶裕貴\n　　　三木眞一郎　花澤香菜　櫻井孝宏　根谷美智子　飛田展男　宮本充　立木文彦 ／ 松たか子\n原作： 岩井俊二 　脚本 ：大根仁  総監督 ：新房昭之　\n企画・プロデュース：川村元気　 監督：武内宣之 　キャラクターデザイン：渡辺明夫　音楽：神前暁　\nアニメーション制作： シャフト\n©2017「打ち上げ花火、下から見るか？横から見るか？」製作委員会\n公開日：2017年８月１８日（金）\n公式ＨＰ：http://uchiagehanabi.jp/\n\n\n\n\n◯ Daoko（ダヲコ）プロフィール\nDaoko（ダヲコ）1997 年⽣まれ、東京都出⾝。\n15 歳の時にニコニコ動画へ投稿した楽曲で注⽬をあつめ、2015 年『DAOKO』でメジャーデビュー。\nその後も⽶津⽞師との「打上花⽕」、岡村靖幸との「ステップアップLOVE」など、実⼒派アーティストとの共作を⾏いつつ、ソロでの活動も続ける。\n⼩説の執筆、絵画個展の開催、女優業など多様なクリエイティヴ表現を続け、国内外で注⽬を集めている。\n2019 年に個⼈事務所“てふてふ”を設⽴し、2020年には4th アルバム『anima』を発表。\n2023年6月に２部作連続で公開予定の劇場版「美少女戦士セーラームーンCosmos」の主題歌を担当。書き下ろし楽曲「月の花」が5月26日(金)に先行配信決定！\n現在は自主レーベル“てふてふ”にて活動中!\n\n◯Official HP　https://daoko.jp\n◯Official Blog　https://daoko.life\n◯Official Twitter\nDAOKO ( https://twitter.com/Daok0 )\nDAOKO staff ( https://twitter.com/DAOKO_staff )\n◯Official Instagram　https://www.instagram.com/daoko_official/\n◯Official Fun Club”ひだまり” 　https://hidamari.daoko.jp/",
        "thumbnails": {
          "default": {
            "url": "https://i.ytimg.com/vi/-tKVN2mAKRI/default.jpg",
            "width": 120,
            "height": 90
          },
          "medium": {
            "url": "https://i.ytimg.com/vi/-tKVN2mAKRI/mqdefault.jpg",
            "width": 320,
            "height": 180
          },
          "high": {
            "url": "https://i.ytimg.com/vi/-tKVN2mAKRI/hqdefault.jpg",
            "width": 480,
            "height": 360
          },
          "standard": {
            "url": "https://i.ytimg.com/vi/-tKVN2mAKRI/sddefault.jpg",
            "width": 640,
            "height": 480
          },
          "maxres": {
            "url": "https://i.ytimg.com/vi/-tKVN2mAKRI/maxresdefault.jpg",
            "width": 1280,
            "height": 720
          }
        },
        "channelTitle": "Synera",
        "playlistId": "PLzJ1mqwxogpFuFCk1YfUE1c0gWtnIutfz",
        "position": 16,
        "resourceId": {
          "kind": "youtube#video",
          "videoId": "-tKVN2mAKRI"
        },
        "videoOwnerChannelTitle": "daoko_jp",
        "videoOwnerChannelId": "UCIzc1_X3OAFquArF3EOVeWw"
      }
    },
    {
      "kind": "youtube#playlistItem",
      "etag": "2pMw-51WDHgOCQ4U6Px-MmtWrUI",
      "id": "UEx6SjFtcXd4b2dwRnVGQ2sxWWZVRTFjMGdXdG5JdXRmei4yMDhBMkNBNjRDMjQxQTg1",
      "snippet": {
        "publishedAt": "2024-03-20T08:23:14Z",
        "channelId": "UCZtzcQ_fiXuw6dNx_AxK7_Q",
        "title": "YOASOBI「アドベンチャー」Official Music Video",
        "description": "Streaming & Download : https://orcd.co/adventure\nMusic : Ayase (https://twitter.com/ayase_0404)\nVocal : ikura (https://twitter.com/ikutalilas)\n\nGuitar : AssH (https://twitter.com/AssH_Guitarist)\n\n原作：「レンズ越しの煌めきを」(著 菜葵)\nhttps://www.usj.co.jp/web/ja/jp/news/2022/1012\n-あらすじ\nユニバーサル・スタジオ・ジャパン－－。15歳の私にとってそこは遥か遠くにある「夢」の空間だった。\nさまざまなことが制限された世の中で、待ち焦がれた瞬間を仲間と分かち合う歓びがエモーショナルに描かれた瑞々しいエピソード。\n\n「特別を生み出す旋律は ～YOASOBI『アドベンチャー』の原作『レンズ越しの煌めきを』アフターストーリー～」(著 菜葵)\nhttps://note.com/yoasobi_staff/n/ne12025858bb2\n\n2023年2月1日(水)より、お気に入りのBGMを選んで、乗車中に聴きながら目の覚めるようなスリルと開放感を体験できる大人気のライド・アトラクション「ハリウッド・ドリーム・ザ・ライド」に期間限定搭載していただきました。\nhttps://www.usj.co.jp/web/ja/jp/attractions/hollywood-dream-the-ride\n\n2022年10月に実施した「YOASOBI×ユニ春 学生応援！エピソード募集キャンペーン」に寄せられた中から、楽曲の原作としてAyase＆ikuraが選出させていただいたエピソードです。応募者の皆さま、本当にありがとうございました！\n\n2023年3月11日ユニバーサル・スタジオ・ジャパンでおこなわれたユニ春！ライブ2023、現地レポートはこちら！\nhttps://note.com/yoasobi_staff/n/n645dacb84020\n\nインスト音源はこちら：https://piapro.jp/t/_Uyj\n\n○ユニバーサル･スタジオ･ジャパン『ユニ春』 新CM\nhttps://www.youtube.com/watch?v=O2kZ5OFwiCg&t=0s\n--\nいつもの一日から抜け出して\n目が覚めるような冒険の舞台へ\n回る地球儀を目印に\nさあ今会いに行こう\n特別な一日に\n\n緑萌ゆる新しい季節に\n一人見つめたブルーライト\n顔も知らない友達にも満たないクラスメイト\n想定外の暮らし\n\nこんなんじゃない\n妄想した理想と真反対に\n淡々と過ぎる毎日\nでもやっと会えるね\n想像と現実が交わって\n高鳴る胸押さえられない\n\n約束の場所は\n夢見ていた場所\n忘れられない一日が\n今始まる\n\n待ちに待った今日は特別な日\n日常から少しはみ出して\nほらシャッターを切って写し出せば\nどうしたって\n零れるような笑顔ばかり\n\n誰かが言い出して飛び乗ったコースターも\nお揃いのカチューシャも\nかけがえの無い瞬間で溢れてる\n待ち時間さえも愛しく思える\n\n次はどこに行こうか\n軽やかに歩く\n不思議なほどに\n気が付けば過ぎている時間 \n\n太陽が沈んだ街を飾る\n光が織りなすパレードに\n心奪われ噛み締める\n本当にここに来れて良かったな\n\n待ちに待った今日は特別な日\nいつも通りから飛び出して\nほらシャッターを切っても写せない\n思い出がいつでも待っている\n春も夏も秋も冬も\nこの場所で見つけた笑顔が\nひらひらと幾つも積もっていく\nさあ次はいつ会いに行けるかな\n\n当たり前から抜け出して\n限界の無い冒険の舞台へ\n回る地球儀を目印に\nさあ今会いに行こう\n特別な一日に \n--\nCreative Producer：Yasuaki Nakagawa\nCreative Director：Rei Hanada\nBusiness Producer : Shunsuke Kimura\n\nDirector：Jun Tamukai (CONNECTION)\n\nCinematographer：Masatoshi Toyonou (SPICE)\n1st Camera Assistant：Shinnosuke Mizuno (SPICE)\n2nd Camera Assistant：Ryo Kawasaki (SPICE)\n3rd Camera Assistant：Kouyou Morita (SPICE)\n\nLighting Director：Tomoyuki Ikeda\n1st Lighting Assistant：Takaori Kidokoro \n2nd Lighting Assistant：Masahiro Inoue/ Yoshikazu Hirose / Shu Yositake / Tatsuya Yamazaki / Tomokazu Sato\nLighting Support Staff：Yosuke Nuka (ARC SYSTEM)\n\nChoreographer：Seishiro (P.I.C.S. management)\nDancer：YUKINA\nCharacter Designer：imid\nProduction Designer：Katsuaki Goto\nStylist：Kenshi Kaneda\nMotion Capture System：XSENS MVN (Zero C Seven)\n\nVFX Supervisor：Takahiro Ota (KASSEN)\nVFX Lead Designer：Kai Inoue (KASSEN)\nVFX Designer：Akiko Aoyama (KASSEN) / Tomoyo Akiyama (KASSEN)\nVFX Producer：Yusuke Makita (KASSEN)\nOnset Supervisor：Ryuji Yagami (KASSEN) \nColorist：Hisashi Nemoto (KASSEN)\nColorist Manager：Heun Lee (KASSEN)\n\nCG Director：Satoshi Takeno (MontBlanc Pictures)\nCG Producer：Taiyo Sato (KASSEN) / Kouhei Miki (KASSEN / HASH)\nCG Production Maneger：Saori Yamagami (HASH) / SHIKO (KASSEN)\n\nCG Producer：Futoshi Nagata (AnimationCafe / CELAVIE)\nCG Production Maneger：Yoshihiro Tanabe (AnimationCafe / CELAVIE)\nCG Animation SV：Shuto Fujisawa (AnimationCafe/CELAVIE)\nCG Animator：Shota Ogura (AnimationCafe / CELAVIE) / Ellie Shimogori (AnimationCafe / CELAVIE) / Ko Yasuda (AnimationCafe / CELAVIE)\n\nTechnical Artist：Hiroyuki Okada (Modeling Cafe) / Takafumi Nakayama (Modeling Cafe)\nRigger：Masashi Mukai (Modeling Cafe) / Ayano Usuda (Modeling Cafe)\n\nCG Animator：Leonie-Marie Lei Arimura (MontBlanc Pictures) / Fuuka Kawaguchi (MontBlanc Pictures)\n\nCG Modeler：Kei Kidera (HASH)\nCG Animator：Kotaro Azuma (HASH)\n\nCG Modeler：Tsukasa Osawa (Alchemy)\nCG Designer：Sanghye Oh \n\nCG Producer：Kosuke Kurokawa (Welz Animation Studios)\nCG Production Maneger：Ryouta Ishi (Welz Animation Studios)\nCG Designer：Shoichi Enomoto (Welz Animation Studios)\nCompositor：Kana Hashimoto (Welz Animation Studios) / Tenna Inami (Welz Animation Studios)\n\nCG Producer：Kito Ogihara (Kilika Collection)\nCG Designer：Takahiro Saito (Kilika Collection) / Hiromi Matsushige (Kilika Collection) / Leo Ogihara (Kilika Collection)\n\nModeling Artist：Takehiko Hoashi (studio picapixels)\nMatch Move Artist ：Naoki Korematsu (CGSLAB)\nCG Animator：Hideki Kojo / Ryo Fujimoto\n\n2D Effects Production：mimoid\nAnimator：Takuto Kawakami (mimoid) / Kana Fukudome (mimoid)\n\nProducer：Mao Suzuki (P.I.C.S.)\nProduction Manager：Koichi Iwamoto (P.I.C.S.)\nProduction Assistant：Yuki Adachi (P.I.C.S.)/ Shogo Honda (P.I.C.S.) / Masakuni Tsujimoto (P.I.C.S.)/ Masakuni Sato (P.I.C.S.)/ Naoki Matsubara (P.I.C.S.)/ Ruka Sakuragi / Hironari Kimura\nProduction：P.I.C.S.\n\nSpecial Thanks：UNIVERSAL STUDIOS JAPAN\n\nTM & © 2023 Sesame Workshop\n© 2023 MARVEL\nTM & © Universal Studios. All rights reserved.\n--\n#YOASOBI #アドベンチャー #ユニ春",
        "thumbnails": {
          "default": {
            "url": "https://i.ytimg.com/vi/Av3xaZkVpJs/default.jpg",
            "width": 120,
            "height": 90
          },
          "medium": {
            "url": "https://i.ytimg.com/vi/Av3xaZkVpJs/mqdefault.jpg",
            "width": 320,
            "height": 180
          },
          "high": {
            "url": "https://i.ytimg.com/vi/Av3xaZkVpJs/hqdefault.jpg",
            "width": 480,
            "height": 360
          },
          "standard": {
            "url": "https://i.ytimg.com/vi/Av3xaZkVpJs/sddefault.jpg",
            "width": 640,
            "height": 480
          },
          "maxres": {
            "url": "https://i.ytimg.com/vi/Av3xaZkVpJs/maxresdefault.jpg",
            "width": 1280,
            "height": 720
          }
        },
        "channelTitle": "Synera",
        "playlistId": "PLzJ1mqwxogpFuFCk1YfUE1c0gWtnIutfz",
        "position": 17,
        "resourceId": {
          "kind": "youtube#video",
          "videoId": "Av3xaZkVpJs"
        },
        "videoOwnerChannelTitle": "Ayase / YOASOBI",
        "videoOwnerChannelId": "UCvpredjG93ifbCP1Y77JyFA"
      }
    },
    {
      "kind": "youtube#playlistItem",
      "etag": "ry89BOEK8T3UGSgYfYDvROtNaAg",
      "id": "UEx6SjFtcXd4b2dwRnVGQ2sxWWZVRTFjMGdXdG5JdXRmei5GM0Q3M0MzMzY5NTJFNTdE",
      "snippet": {
        "publishedAt": "2024-03-20T08:23:26Z",
        "channelId": "UCZtzcQ_fiXuw6dNx_AxK7_Q",
        "title": "YOASOBI「怪物」Official Music Video　(YOASOBI - Monster)",
        "description": "Download＆Streaming配信中:https://orcd.co/kaibutsu\nTVアニメ『BEASTARS』第二期オープニングテーマ\n『BEASTARS』原作者・板垣巴瑠先生がこの楽曲の原作小説として書き下ろした「自分の胸に自分の耳を押し当てて」はTVアニメBEASTARS公式HP[MUSIC]タブにて公開中！\nhttps://bst-anime.com/\n--\nTVアニメ『BEASTARS』第二期エンディングテーマ「優しい彗星」もぜひ合わせてお聴きください。\nhttps://youtu.be/VyvhvlYvRnc\n--\nシングル『怪物/優しい彗星』3月24日発売！ご予約はこちら。\n-アニメ盤\nhttps://yoasobi.lnk.to/XSCL-54\n\n-YOASOBIオフィシャルファンクラブ\"CLUB 夜遊\"限定盤\nhttps://yoasobi-fc.com/0303\n--\n\n●YOASOBI：https://twitter.com/YOASOBI_staff\nComposer : Ayase (https://twitter.com/ayase_0404)\nVocal : ikura (https://twitter.com/ikutalilas )\n\n●MUSIC VIDEO\n-ディレクション Direction\n三皷梨菜(ハイパーボール) Rina Mitsuzumi(Hyperbole Inc.)\n\n-モーショングラフィックス Motion Graphics\n松田潤(ツー・ワイディー) Jun Matsuda(TWO WAIDEE INC.)\nカフウ(Argument) Cafuu (Argument)\n\n-2Dアニメーション 2D Animation\nオオニシカオリ Kaori Onishi \n\n-デザイン協力 Design Support\nAIりんな AI Rinna\n\n★インスト音源はこちら\nhttps://piapro.jp/t/yr5P\n\n--\n素晴らしき世界に今日も乾杯\n街に飛び交う笑い声も\n見て見ぬフリしてるだけの作りもんさ\n気が触れそうだ\nクラクラするほどの良い匂いが\nツンと刺した鼻の奥\n目を覚ます本能のまま\n今日は誰の番だ？\n\nこの世界で何が出来るのか\n僕には何が出来るのか\nただその真っ黒な目から\n涙溢れ落ちないように\n\n願う未来に何度でもずっと\n喰らいつく\nこの間違いだらけの世界の中\n君には笑ってほしいから\nもう誰も傷付けない\n強く強くなりたいんだよ\n僕が僕でいられるように\n\n素晴らしき世界は今日も安泰\n街に渦巻く悪い話も\n知らない知らないフリして目を逸らした\n正気の沙汰じゃないな\n真面目に着飾った行進\n鳴らす足音が弾む行き先は\n消えない消えない味が染み付いている\n裏側の世界\n\n清く正しく生きること\n誰も悲しませずに生きること\nはみ出さず真っ直ぐに生きること\nそれが間違わないで生きること？\nありのまま生きることが正義か\n騙し騙し生きるのは正義か\n僕の在るべき姿とはなんだ\n本当の僕は何者なんだ\n教えてくれよ\n教えてくれよ\n\n今日も\n答えのない世界の中で\n願ってるんだよ\n不器用だけれど\nいつまでも君とただ\n笑っていたいから\n跳ねる心臓が\n体揺らし叫ぶんだよ\n今こそ動き出せ\n\n弱い自分を何度でもずっと\n喰らい尽くす\nこの間違いだらけの世界の中\n君には笑ってほしいから\nもう誰も泣かないよう\n強く強くなりたいんだよ\n僕が僕でいられるように\n\nただ君を守るそのために\n走る走る走るんだよ\n僕の中の僕を超える\n--\n#怪物 #BEASTARS #YOASOBI #Monster #Ayase",
        "thumbnails": {
          "default": {
            "url": "https://i.ytimg.com/vi/dy90tA3TT1c/default.jpg",
            "width": 120,
            "height": 90
          },
          "medium": {
            "url": "https://i.ytimg.com/vi/dy90tA3TT1c/mqdefault.jpg",
            "width": 320,
            "height": 180
          },
          "high": {
            "url": "https://i.ytimg.com/vi/dy90tA3TT1c/hqdefault.jpg",
            "width": 480,
            "height": 360
          },
          "standard": {
            "url": "https://i.ytimg.com/vi/dy90tA3TT1c/sddefault.jpg",
            "width": 640,
            "height": 480
          },
          "maxres": {
            "url": "https://i.ytimg.com/vi/dy90tA3TT1c/maxresdefault.jpg",
            "width": 1280,
            "height": 720
          }
        },
        "channelTitle": "Synera",
        "playlistId": "PLzJ1mqwxogpFuFCk1YfUE1c0gWtnIutfz",
        "position": 18,
        "resourceId": {
          "kind": "youtube#video",
          "videoId": "dy90tA3TT1c"
        },
        "videoOwnerChannelTitle": "Ayase / YOASOBI",
        "videoOwnerChannelId": "UCvpredjG93ifbCP1Y77JyFA"
      }
    },
    {
      "kind": "youtube#playlistItem",
      "etag": "Kgk9JHsMUU7Nvhup3qBXfHPWmWg",
      "id": "UEx6SjFtcXd4b2dwRnVGQ2sxWWZVRTFjMGdXdG5JdXRmei4zRjM0MkVCRTg0MkYyQTM0",
      "snippet": {
        "publishedAt": "2024-03-20T08:23:49Z",
        "channelId": "UCZtzcQ_fiXuw6dNx_AxK7_Q",
        "title": "「ツバメ」/ YOASOBI with ミドリーズ Official Music Video",
        "description": "「ツバメ」ストリーミング＆ダウンロード絶賛配信中\nhttps://orcd.co/tsubame\n2nd EP『THE BOOK 2』発売中！\nDigital：https://YOASOBI.lnk.to/THE_BOOK_2\nPhysical：https://orcd.co/thebook2\n\nNHK子ども向けSDGs番組シリーズ「ひろがれ！いろとりどり」テーマソング\nhttps://www.nhk.or.jp/irotoridori/\n\n原作小説「小さなツバメの大きな夢」(乙月なな 著)\nhttps://www.nhk.or.jp/irotoridori/song/\n\nダンスミュージックビデオ フルver. \nhttps://youtu.be/9r_LWmw4gok\n\nMusic : Ayase (https://twitter.com/ayase_0404)\nVocal : ikura (https://twitter.com/ikutalilas)\nGuitar：AssH(https://twitter.com/AssH_Guitarist)\nChorus：ミドリーズ (あつき、レクシー、うきょう、りりな、ゆめり)\n\nMusic Video by 藍にいな(https://twitter.com/nina_o0o0 )\n\nインスト音源はこちら\nhttps://piapro.jp/t/b1Sp\n--\n煌く水面の上を\n夢中で風切り翔る\n翼をはためかせて\nあの街へ行こう\n海を越えて\n\n僕はそう小さなツバメ\n辿り着いた街で触れた\n楽しそうな人の声\n悲しみに暮れる仲間の声\n\nみんなそれぞれ違う暮らしの形\n守りたくて気付かないうちに\n傷付け合ってしまうのはなぜ\n同じ空の下で\n\n僕らは色とりどりの命と\nこの場所で共に生きている\nそれぞれ人も草木も花も鳥も\n肩寄せ合いながら\n僕らは求めるものも\n描いてる未来も違うけれど\n手と手を取り合えたなら\nきっと笑い合える日が来るから\n僕にはいま何ができるかな\n\n誰かが手に入れた豊かさの裏で\n帰る場所を奪われた仲間\n本当は彼も寄り添い合って\n生きていたいだけなのに\n\n悲しい気持ちに飲み込まれて\n心が黒く染まりかけても\n許すことで認めることで\n僕らは繋がり合える\n\n僕らにいまできること\nそれだけで全てが変わらなくたって\n誰かの一日にほら\n少しだけ鮮やかな彩りを\n輝く宝石だとか\n金箔ではないけれど\nこんな風に世界中が\nささやかな愛で溢れたなら\n何かがほら変わるはずさ\n同じ空の下いつかきっと\nそれが小さな僕の大きな夢\n---\n#YOASOBI #ツバメ #ミドリーズ",
        "thumbnails": {
          "default": {
            "url": "https://i.ytimg.com/vi/qDL3zhB8-MM/default.jpg",
            "width": 120,
            "height": 90
          },
          "medium": {
            "url": "https://i.ytimg.com/vi/qDL3zhB8-MM/mqdefault.jpg",
            "width": 320,
            "height": 180
          },
          "high": {
            "url": "https://i.ytimg.com/vi/qDL3zhB8-MM/hqdefault.jpg",
            "width": 480,
            "height": 360
          },
          "standard": {
            "url": "https://i.ytimg.com/vi/qDL3zhB8-MM/sddefault.jpg",
            "width": 640,
            "height": 480
          },
          "maxres": {
            "url": "https://i.ytimg.com/vi/qDL3zhB8-MM/maxresdefault.jpg",
            "width": 1280,
            "height": 720
          }
        },
        "channelTitle": "Synera",
        "playlistId": "PLzJ1mqwxogpFuFCk1YfUE1c0gWtnIutfz",
        "position": 19,
        "resourceId": {
          "kind": "youtube#video",
          "videoId": "qDL3zhB8-MM"
        },
        "videoOwnerChannelTitle": "Ayase / YOASOBI",
        "videoOwnerChannelId": "UCvpredjG93ifbCP1Y77JyFA"
      }
    },
    {
      "kind": "youtube#playlistItem",
      "etag": "NP4IPQ9ygAno8Fa-QUs6aVNmsDk",
      "id": "UEx6SjFtcXd4b2dwRnVGQ2sxWWZVRTFjMGdXdG5JdXRmei45NzUwQkI1M0UxNThBMkU0",
      "snippet": {
        "publishedAt": "2024-03-20T08:24:04Z",
        "channelId": "UCZtzcQ_fiXuw6dNx_AxK7_Q",
        "title": "YOASOBI「大正浪漫」Official Music Video",
        "description": "ストリーミング/ダウンロード絶賛配信中\nhttps://orcd.co/taisho_romance\n\nMusic : Ayase (https://twitter.com/ayase_0404)\nVocal : ikura (https://twitter.com/ikutalilas)\n\nインスト音源はこちら\nhttps://piapro.jp/t/RigK\n\n-原作小説\n『大正浪漫 YOASOBI「大正浪漫」原作小説』\n○Blu-rayつき限定版\n著者：NATSUMI\n発売日：2021年09月16日\n定価：2,970円（本体2,700円＋税）\n判型：四六判上製\n-特別版限定特典\n・楽曲「大正浪漫」「もう少しだけ」のSpecial Session ikura with ハラミちゃんを収録したBlu-ray\n・オリジナルポストカード\n・オリジナルしおり\n-限定版/通常版共通特典映像\nikuraによる小説『大正浪漫』朗読映像\n\n○通常版\n著者：NATSUMI\n発売日：2021年09月16日\n定価：1,485円（本体1,350円＋税）\n判型：四六判上製\n-限定版/通常版共通特典映像\nikuraによる小説『大正浪漫』朗読映像\n\n詳細はこちら\nhttps://yoasobi-book.futabasha.com/\n\n原案「大正ロマンス」\nhttps://monogatary.com/story/78167\n-あらすじ\n時翔のもとに届いた不思議な手紙。\n100年前を生きる千代子が書いたものらしい。\n思いがけず始まった“文通”で距離を縮めるふたりだったが＿＿＿\n令和と大正、時を超えた恋の行方は?\n--\nある日突然にそれは\n訪れた出来事\n始まりは一通の手紙\n送り主は遥か昔を生きる君\nそんな不可思議な出会い\n\n僕の時代には今\nこんなものがあって\nこんな暮らしをしているよ\n文字に込めて伝え合ううちに\nいつしか芽生えたロマンス\n\n決して出会うことの出来ない僕ら\nそれぞれの世界から\n綴る言葉\n募る想い\n姿さえも\n知らないまま\n\nどんな時も君の言葉を\n待ち焦がれているんだ\n生きる時代は違うけど\n何度でも時間を越えて\n君と伝え合う想い\n願いが叶うなら\n一目でいいから\n会いたいな\n好きだから\n\n不意に思い出したのは\n君が生きる時代の明日\n起こること\n悲しいこと\n伝えなくちゃ\nどうか奇跡よ起きて\n\n過ぎていく時と\n変わる季節\nあれから途絶えた手紙\nもう届かない言葉だけが胸を締めつける\n\n遥か彼方100年先を\n君が見てみたいと願った未来を今\n僕はまだ歩いているよ\n苦しい想いを胸に抱いたまま\nそんな僕に届いた手紙\n見覚えのある待ち焦がれていた文字\nそれは君があの日を越えて\n僕に書いた最後の恋文\n君が君の時代を生きた証を\n八千代越えても握りしめて\n僕が僕の時代に見るその全てを\nいつか伝えに行くよ\n--\n★Music Video\n■監督/絵コンテ/世界観設計\n高瀬 裕介\n\n■キャラクターデザイン\n窪之内 英策\n\n■作画監督\n名倉 靖博\n\n■美術監督\n木村 真二\n\n■世界観CG監督\n平川 侑樹\n\n■キャラクターCG監督\n森江 康太\n\n■アニメーションプロデューサー\n鈴木 隆介\n\n■CG プロデューサー\n阪田 俊彦\n\n■アニメーション制作\nシャフト\n\n■原画\n西澤 真也　河島 久美子　大橋 勇吾　本田 陸　一ノ瀬 結梨\n名倉 靖博\n\n■第二原画\n上野 あさみ　大谷 洋一朗　志村 亮　\n\n■動画\nパディジカ ダニエラ　山田 詩乃　徐 靖媛　許 有真　内田 百香　舟山 桜　楊 智開\n徳留 夢奈　河上 伸太郎　櫻井 萌美　森 幸香\n黄 旻淳　古川 嗣英　村上 朋子　松戸 美樹\n\n竹縄 利名\n\n■動画検査\n勝冶 果歩\n\n■色彩設計/色指定/検査\n渡辺 康子\n\n■仕上げ\n服部 文美　川上 優子　林 恩羽\n\n角 美智子\n\n■セルコンポジット\n会津 孝幸\n\n■世界観CG制作\n(+Ring)\n勝野 健太\n山口 綺香　岩城 司　三浦 大輝　山田 明歩\n\n(LiPOGRAM)\n木村 未佑　東 拓矢　加藤 夏実\n\n(モデリングブロス)\n今泉 隼介　箕浦 佑　仲條 駿輔　黒土 楓花　成生 佳穂\n\n（Freelance）\n松浦 泰仁　水戸部 智史\n\n■キャラクターCG制作\n(MORIE Inc.)\n柴野 剛宏\n冨田 直人　白井 麻理江　田島 誠人　木寺 桂\n小川 光悦　菅原 愁也　北岡 明佑子　酒井 健人\n丹原 亮　東 孝太郎　大野 陽祐\n\n(トランジスタ・スタジオ)\n金山 隼人\n\n■オンライン編集\n佐々木 賢一　久藤 拓実\n\n■プロデューサー\n(HATCH Inc.)\n本間 綾一郎　黒田 正風　前川 達哉\n\n■テキストデザイン\n前田 定則\n\n■制作進行\n馮 灝　原田 季和\n\n■アニメーション制作協力\n(グラフィニカ)\n平澤 直　大塚 未侑\n\n■プレビズ制作\n(LUDENS)\n渡部 暁　荻野 夏生　佐藤 昭宏　\n上野 雅志　清水 亮　牧田 聡　石ヶ谷 宜昭　\nsankaku\n\n■クリエイティブディレクター\n(STARBASE INC.)\n日髙 良太郎\n\n■クリエティブプロデューサー\n(STARBASE INC.)\n青沼 弘樹\n\n■制作\nQuadratic Playground by NTT DOCOMO,INC.\nhttps://www.qplay.jp/\n\n--\n#YOASOBI #大正浪漫",
        "thumbnails": {
          "default": {
            "url": "https://i.ytimg.com/vi/wJQ9ig_d8yY/default.jpg",
            "width": 120,
            "height": 90
          },
          "medium": {
            "url": "https://i.ytimg.com/vi/wJQ9ig_d8yY/mqdefault.jpg",
            "width": 320,
            "height": 180
          },
          "high": {
            "url": "https://i.ytimg.com/vi/wJQ9ig_d8yY/hqdefault.jpg",
            "width": 480,
            "height": 360
          },
          "standard": {
            "url": "https://i.ytimg.com/vi/wJQ9ig_d8yY/sddefault.jpg",
            "width": 640,
            "height": 480
          },
          "maxres": {
            "url": "https://i.ytimg.com/vi/wJQ9ig_d8yY/maxresdefault.jpg",
            "width": 1280,
            "height": 720
          }
        },
        "channelTitle": "Synera",
        "playlistId": "PLzJ1mqwxogpFuFCk1YfUE1c0gWtnIutfz",
        "position": 20,
        "resourceId": {
          "kind": "youtube#video",
          "videoId": "wJQ9ig_d8yY"
        },
        "videoOwnerChannelTitle": "Ayase / YOASOBI",
        "videoOwnerChannelId": "UCvpredjG93ifbCP1Y77JyFA"
      }
    },
    {
      "kind": "youtube#playlistItem",
      "etag": "aHjRl-FH0qWDQbcwcsMxkod9PoM",
      "id": "UEx6SjFtcXd4b2dwRnVGQ2sxWWZVRTFjMGdXdG5JdXRmei5DNzE1RjZEMUZCMjA0RDBB",
      "snippet": {
        "publishedAt": "2024-03-20T08:25:07Z",
        "channelId": "UCZtzcQ_fiXuw6dNx_AxK7_Q",
        "title": "YOASOBI「もしも命が描けたら」Official Music Video",
        "description": "ストリーミング＆ダウンロード配信中\nhttps://orcd.co/thebook2\n\n舞台「もしも命が描けたら」テーマ曲\nhttps://tristone.co.jp/moshimoinochi/\n戯曲「もしも命が描けたら」全編公開中\nhttps://www.yoasobi-music.jp/novels/moshimoinochigaegaketara/\n\nMusic : Ayase (https://twitter.com/ayase_0404)\nVocal : ikura (https://twitter.com/ikutalilas)\n\n・Music Video\nDirector / Storyboard / Key Animator：清川あさみ\nAnimation Director：稲葉秀樹(P.I.C.S. management)\nAnimation Producer：松居秀之[P.I.C.S]\n\nインスト音源はこちら\nhttps://piapro.jp/t/yrPP\n---\n月が綺麗な夜に\n森の中でただひとり\nこの世界から旅立つ前に\nこれまでの日々を浮かべる\n\n裕福じゃない暮らしそれでも\nいつだってそばには母の優しさ\n僕の描く絵を大好きだと言ってくれた人\n二人生きるために夢も捨て働いて\nそれでも訪れる別れ\nそんな時に君に出会い\n恋に落ちた\n愛を知った\n\n幸せだと\n思えたのに\nどうして\n大切なものばかりが\n消えていく\nこの世界と\nさよならしよう\n\n会いに行くよ今すぐそこへ\n君がいるところまで\n愛してるごめんね\nその時君の声が聞こえた\nそうやって自分で全てを\n終わりにしてしまえばもう\n誰にも会えないんだよずっと\n満月の夜に\n\nLala…\n\n終わらせることができず\n地面に落ちた僕に突然\n月が話しかけてきた\nそして不思議な力をくれた\n描いたものに命を分け与える力\n枯れかけた草木も息を吹き返す\n僕の残りの時間と引き換えに\n\n描いていくこの命を元に\n少しずつ分け与えていく\n生きる意味ができたんだ\nそんな時あなたと出会った\n同じように悲しみの中で生きている人\n自ら旅立とうとした僕を怒ってくれた人\nいつの間にか惹かれていった\n\nだけどあなたには愛する人がいる\nあなたを裏切ったひどい人\nそれでもあなたが愛してしまう人\nそんな彼の命が今消えかけている\n\n泣きながら彼の名前を叫ぶ\nあなたを見て決めた\n一日だけ残して\n僕の命全て捧げて描いた\nそして彼は目を覚ました\n\n嗚呼僕が起こした奇跡に\n涙流し喜ぶあなたに\nどうしても伝えたい\n僕の想いを最期に聞いて\nこうやって生きる喜びを\n与えてくれたあなたが\n本当に大好きでした\nさよなら\n\nLala…\n\nそしてひとり\nあなたのこと母のこと\n君のこと想い目を瞑った\n長い長い旅の終わり\nやっとまた会えたね\n--\n#YOASOBI #もしも命が描けたら #清川あさみ",
        "thumbnails": {
          "default": {
            "url": "https://i.ytimg.com/vi/I0kytvnHG-Q/default.jpg",
            "width": 120,
            "height": 90
          },
          "medium": {
            "url": "https://i.ytimg.com/vi/I0kytvnHG-Q/mqdefault.jpg",
            "width": 320,
            "height": 180
          },
          "high": {
            "url": "https://i.ytimg.com/vi/I0kytvnHG-Q/hqdefault.jpg",
            "width": 480,
            "height": 360
          },
          "standard": {
            "url": "https://i.ytimg.com/vi/I0kytvnHG-Q/sddefault.jpg",
            "width": 640,
            "height": 480
          },
          "maxres": {
            "url": "https://i.ytimg.com/vi/I0kytvnHG-Q/maxresdefault.jpg",
            "width": 1280,
            "height": 720
          }
        },
        "channelTitle": "Synera",
        "playlistId": "PLzJ1mqwxogpFuFCk1YfUE1c0gWtnIutfz",
        "position": 21,
        "resourceId": {
          "kind": "youtube#video",
          "videoId": "I0kytvnHG-Q"
        },
        "videoOwnerChannelTitle": "Ayase / YOASOBI",
        "videoOwnerChannelId": "UCvpredjG93ifbCP1Y77JyFA"
      }
    },
    {
      "kind": "youtube#playlistItem",
      "etag": "haNf5XIgYf7wpDH5Gn5fU8lNrSg",
      "id": "UEx6SjFtcXd4b2dwRnVGQ2sxWWZVRTFjMGdXdG5JdXRmei43MTI1NDIwOTMwQjIxMzNG",
      "snippet": {
        "publishedAt": "2024-03-20T08:25:27Z",
        "channelId": "UCZtzcQ_fiXuw6dNx_AxK7_Q",
        "title": "【女性が歌う】back number / HAPPY BIRTHDAY (Covered by コバソロ & 藤川千愛)",
        "description": "今回はTBS系火曜ドラマ「初めて恋をした日に読む話」主題歌、back numberさんの HAPPY BIRTHDAY をカバーしました。今回のボーカルは藤川千愛さん！チャンネル登録してね！▶︎ https://www.youtube.com/user/Hujikoman\n\n【藤川千愛】\nTwitter:  https://twitter.com/fujikawachiai\nInstagram:  https://www.instagram.com/fujikawa_chiai/\nYoutube:  https://www.youtube.com/channel/UCPn4XA6Gb2u8y_FXXtrHW7w\n音楽配信:  https://nippon-columbia.lnk.to/9GTDu\nOfficial HP:  https://fujikawachiai.com/\n\n【RELEASE INFORMATION】\n⚫︎⚫︎⚫︎⚫︎⚫︎Original⚫︎⚫︎⚫︎⚫︎⚫︎\n\n★2nd album「Clumsy」\n配信サイト一覧→https://linkco.re/prxtScat\n\n★1st full album「KOBASOLO」\n配信サイト一覧→ https://linkco.re/cy6VH9VX\nCD通販→ https://kobasolo.stores.jp\n\n⚫︎⚫︎⚫︎⚫︎⚫︎Cover⚫︎⚫︎⚫︎⚫︎⚫︎\n\n★2nd Cover Album「これくしょん２」NEW!!\n配信サイト一覧→ https://vap.lnk.to/collection2\nAmazon→ https://www.amazon.co.jp/dp/B07KZ1Y2Q5/ref=cm_sw_r_tw_dp_U_x_Dd1FCbA45JPNM\n全国CDショップやAmazon、楽天などでも発売中!!\n\n★1st Cover Album「これくしょん」\n配信サイト一覧→ https://vap.lnk.to/correction\nAmazon→ https://www.amazon.co.jp/dp/B073WSPGM5/ref=cm_sw_r_tw_dp_U_x_Se1FCbV3TWWHN\n全国CDショップやAmazon、楽天などでも発売中!!\n\n★コバソロ & 未来 \n配信限定EP「MIRAI COVERS」\n配信サイト一覧→ https://umj.lnk.to/zxNBB\n\n★Cover Album「これくしょん」特設サイトhttp://www.vap.co.jp/kobasolo/\n\n⚫︎⚫︎⚫︎⚫︎⚫︎⚫︎⚫︎⚫︎⚫︎⚫︎⚫︎⚫︎⚫︎⚫︎⚫︎⚫︎⚫︎⚫︎⚫︎⚫︎⚫︎⚫︎⚫︎⚫︎⚫︎⚫︎⚫︎⚫︎⚫︎⚫︎⚫︎⚫︎⚫︎⚫︎⚫︎\n\n【コバソロ/Kobasolo】\nYouTube▶︎http://www.youtube.com/user/Hujikoman\n2ndチャンネル▶︎https://goo.gl/FuH0aR\nTwitter▶︎https://twitter.com/kobamakolts\nfacebook▶︎http://www.facebook.com/#!/kobasolo\ninstagram▶︎http://instagram.com/kobasolo/\nHP▶︎http://kobasolo.net/\nオンラインショップ▶︎https://kobasolo.stores.jp\n\n【オリジナル曲MV】\n★エンディング曲\n『君さえいなけりゃ feat. 春茶/コバソロ』\niTunes▶︎https://apple.co/2jMiMvi\nMV▶︎https://youtu.be/-KOeQapXsx8\n\n【使用機材】───────────────\n●カメラ(2012〜2016)https://amzn.to/2U54NEF\n● カメラ(2017〜)https://amzn.to/2Wf6v3F\nhttps://amzn.to/2JqOw8T\n\n●レンズ\nhttps://amzn.to/2WdXqYN\nhttps://amzn.to/2Jrs7Ik\nhttps://amzn.to/2HL91dN\n\n●スタビライザー\nhttps://amzn.to/2FoeUfs\nhttps://amzn.to/2Wdf9zC\n\n●照明\nhttps://amzn.to/2HJ6IYK\nhttps://amzn.to/2WdIxWb\n\n●DTMソフト\nhttps://amzn.to/2TNEcwd\n\n●ヘッドホン\nhttps://amzn.to/2Fo5CAc\n\n●オーディオインターフェース\nhttps://amzn.to/2FpX7ok\n\n●コンデンサーマイク\nhttps://amzn.to/2TWRKVp\nhttps://amzn.to/2W6vc1S\n\n※上記製品リンクURLはAmazonアソシエイトのリンクを使用しています。\n\n■─────────────────────────────────■\nThis video is\nFilmed by kobasolo\nEdited by kobasolo\nAudio produced by kobasolo\n#藤川千愛 #盾の勇者の成り上がり #初めて恋をした日に読む話",
        "thumbnails": {
          "default": {
            "url": "https://i.ytimg.com/vi/PYhCIS29gtc/default.jpg",
            "width": 120,
            "height": 90
          },
          "medium": {
            "url": "https://i.ytimg.com/vi/PYhCIS29gtc/mqdefault.jpg",
            "width": 320,
            "height": 180
          },
          "high": {
            "url": "https://i.ytimg.com/vi/PYhCIS29gtc/hqdefault.jpg",
            "width": 480,
            "height": 360
          },
          "standard": {
            "url": "https://i.ytimg.com/vi/PYhCIS29gtc/sddefault.jpg",
            "width": 640,
            "height": 480
          },
          "maxres": {
            "url": "https://i.ytimg.com/vi/PYhCIS29gtc/maxresdefault.jpg",
            "width": 1280,
            "height": 720
          }
        },
        "channelTitle": "Synera",
        "playlistId": "PLzJ1mqwxogpFuFCk1YfUE1c0gWtnIutfz",
        "position": 22,
        "resourceId": {
          "kind": "youtube#video",
          "videoId": "PYhCIS29gtc"
        },
        "videoOwnerChannelTitle": "kobasolo",
        "videoOwnerChannelId": "UCDbQblY1XASbgqOXmy6FOFQ"
      }
    },
    {
      "kind": "youtube#playlistItem",
      "etag": "yH-bcyoQypFX0_tTN0UnojEiLYs",
      "id": "UEx6SjFtcXd4b2dwRnVGQ2sxWWZVRTFjMGdXdG5JdXRmei5DQ0MyQ0Y4Mzg0M0VGOEYw",
      "snippet": {
        "publishedAt": "2024-03-20T08:26:00Z",
        "channelId": "UCZtzcQ_fiXuw6dNx_AxK7_Q",
        "title": "back number - ハッピーエンド (full)",
        "description": "back number\n16th single「ハッピーエンド」(2016.11.16 Release)\n\nー収録アルバムー\nbest album「アンコール」\n\n※映画「ぼくは明日、昨日のきみとデートする」主題歌\n\n============================================ \n\n▼back number (バックナンバー) LINK\nofficial HP\nhttp://backnumber.info/\nTwitter\nhttps://twitter.com/backnumberstaff\nInstagram\nhttps://www.instagram.com/back_number_official/\nLINE\nhttps://line.me/R/ti/p/@backnumber\nYouTube\nhttps://www.youtube.com/c/backnumberchannel\nTikTok\nhttps://www.tiktok.com/@back_number_official\nWeibo\nhttps://weibo.com/backnumberofficial\ndownload & stream\nhttps://umj.lnk.to/backnumber_st\n\n============================================",
        "thumbnails": {
          "default": {
            "url": "https://i.ytimg.com/vi/T8y_RsF4TSw/default.jpg",
            "width": 120,
            "height": 90
          },
          "medium": {
            "url": "https://i.ytimg.com/vi/T8y_RsF4TSw/mqdefault.jpg",
            "width": 320,
            "height": 180
          },
          "high": {
            "url": "https://i.ytimg.com/vi/T8y_RsF4TSw/hqdefault.jpg",
            "width": 480,
            "height": 360
          },
          "standard": {
            "url": "https://i.ytimg.com/vi/T8y_RsF4TSw/sddefault.jpg",
            "width": 640,
            "height": 480
          },
          "maxres": {
            "url": "https://i.ytimg.com/vi/T8y_RsF4TSw/maxresdefault.jpg",
            "width": 1280,
            "height": 720
          }
        },
        "channelTitle": "Synera",
        "playlistId": "PLzJ1mqwxogpFuFCk1YfUE1c0gWtnIutfz",
        "position": 23,
        "resourceId": {
          "kind": "youtube#video",
          "videoId": "T8y_RsF4TSw"
        },
        "videoOwnerChannelTitle": "BackNumberVEVO",
        "videoOwnerChannelId": "UCb4nKpOlWpZ-bbe-QANF51Q"
      }
    },
    {
      "kind": "youtube#playlistItem",
      "etag": "JZ2HQQG8vqbjVOSvLjaMQZ3_C2Y",
      "id": "UEx6SjFtcXd4b2dwRnVGQ2sxWWZVRTFjMGdXdG5JdXRmei4yQUE2Q0JEMTk4NTM3RTZC",
      "snippet": {
        "publishedAt": "2024-03-20T08:26:16Z",
        "channelId": "UCZtzcQ_fiXuw6dNx_AxK7_Q",
        "title": "【女性が歌う】ヒロイン/back number (Full Cover by Kobasolo & 杏沙子)",
        "description": "今回はbacknumberのヒロインをカバーしました。今回Voをしてくれたのはシンガーソングライターの杏沙子さん。チャンネル登録してね！▶︎ https://www.youtube.com/user/Hujikoman\n【RELEASE INFORMATION】\n⚫︎⚫︎⚫︎⚫︎⚫︎Original⚫︎⚫︎⚫︎⚫︎⚫︎\n\n★2019.3.26 Release!!\n配信限定2nd album「Clumsy」\n1500円\n配信サイト一覧→https://linkco.re/prxtScat\n収録曲\nM1 どうか幸せにならないで feat. 春茶\nM2 新世界のユーツ feat. SiN\nM3 会いたくて feat. こぴ\nM4 夏恋慕 feat. 春茶\nM5 春に揺られど君想う feat. こぴ\nM6 ラブレター feat. 春茶\nM7 言葉さがし feat. こぴ & SiN\nM8 outro\n\n★1st full album「KOBASOLO」\n配信サイト一覧→ https://linkco.re/cy6VH9VX\nCD通販→ https://kobasolo.stores.jp\n\n⚫︎⚫︎⚫︎⚫︎⚫︎Cover⚫︎⚫︎⚫︎⚫︎⚫︎\n\n★2nd Cover Album「これくしょん２」NEW!!\n配信サイト一覧→ https://vap.lnk.to/collection2\nAmazon→ https://www.amazon.co.jp/dp/B07KZ1Y2Q5/ref=cm_sw_r_tw_dp_U_x_Dd1FCbA45JPNM\n全国CDショップやAmazon、楽天などでも発売中!!\n\n★1st Cover Album「これくしょん」\n配信サイト一覧→ https://vap.lnk.to/correction\nAmazon→ https://www.amazon.co.jp/dp/B073WSPGM5/ref=cm_sw_r_tw_dp_U_x_Se1FCbV3TWWHN\n全国CDショップやAmazon、楽天などでも発売中!!\n\n★コバソロ & 未来 \n配信限定EP「MIRAI COVERS」\n配信サイト一覧→ https://umj.lnk.to/zxNBB\n\n★Cover Album「これくしょん」特設サイトhttp://www.vap.co.jp/kobasolo/\n\n⚫︎⚫︎⚫︎⚫︎⚫︎⚫︎⚫︎⚫︎⚫︎⚫︎⚫︎⚫︎⚫︎⚫︎⚫︎⚫︎⚫︎⚫︎⚫︎⚫︎⚫︎⚫︎⚫︎⚫︎⚫︎⚫︎⚫︎⚫︎⚫︎⚫︎⚫︎⚫︎⚫︎⚫︎⚫︎\n\n【コバソロ/Kobasolo】\nYouTube▶︎http://www.youtube.com/user/Hujikoman\n2ndチャンネル▶︎https://goo.gl/FuH0aR\niTunes▶︎https://goo.gl/uNuMgQ\nTwitter▶︎https://twitter.com/kobamakolts\nfacebook▶︎http://www.facebook.com/#!/kobasolo\n\n【杏沙子】\nYouTube▶︎https://goo.gl/7FIW8l\nTwitter▶︎https://twitter.com/asako_ssw\nnana▶︎http://hibari.nana-music.com/w/profile/1218924/\n\n【使用機材】───────────────\n●カメラ(2012〜2016)https://amzn.to/2U54NEF\n● カメラ(2017〜)https://amzn.to/2Wf6v3F\nhttps://amzn.to/2JqOw8T\n\n●レンズ\nhttps://amzn.to/2WdXqYN\nhttps://amzn.to/2Jrs7Ik\nhttps://amzn.to/2HL91dN\n\n●スタビライザー\nhttps://amzn.to/2FoeUfs\nhttps://amzn.to/2Wdf9zC\n\n●照明\nhttps://amzn.to/2HJ6IYK\nhttps://amzn.to/2WdIxWb\n\n●DTMソフト\nhttps://amzn.to/2TNEcwd\n\n●ヘッドホン\nhttps://amzn.to/2Fo5CAc\n\n●オーディオインターフェース\nhttps://amzn.to/2FpX7ok\n\n●コンデンサーマイク\nhttps://amzn.to/2TWRKVp\nhttps://amzn.to/2W6vc1S\n\n※上記製品リンクURLはAmazonアソシエイトのリンクを使用しています。\n\n■─────────────────────────────────■\nThis video is\nFilmed by kobasolo\nEdited by kobasolo\nAudio produced by kobasolo",
        "thumbnails": {
          "default": {
            "url": "https://i.ytimg.com/vi/saq0a2eG5y4/default.jpg",
            "width": 120,
            "height": 90
          },
          "medium": {
            "url": "https://i.ytimg.com/vi/saq0a2eG5y4/mqdefault.jpg",
            "width": 320,
            "height": 180
          },
          "high": {
            "url": "https://i.ytimg.com/vi/saq0a2eG5y4/hqdefault.jpg",
            "width": 480,
            "height": 360
          },
          "standard": {
            "url": "https://i.ytimg.com/vi/saq0a2eG5y4/sddefault.jpg",
            "width": 640,
            "height": 480
          },
          "maxres": {
            "url": "https://i.ytimg.com/vi/saq0a2eG5y4/maxresdefault.jpg",
            "width": 1280,
            "height": 720
          }
        },
        "channelTitle": "Synera",
        "playlistId": "PLzJ1mqwxogpFuFCk1YfUE1c0gWtnIutfz",
        "position": 24,
        "resourceId": {
          "kind": "youtube#video",
          "videoId": "saq0a2eG5y4"
        },
        "videoOwnerChannelTitle": "kobasolo",
        "videoOwnerChannelId": "UCDbQblY1XASbgqOXmy6FOFQ"
      }
    },
    {
      "kind": "youtube#playlistItem",
      "etag": "858WJiZgpGriqbknn53tTf19RYw",
      "id": "UEx6SjFtcXd4b2dwRnVGQ2sxWWZVRTFjMGdXdG5JdXRmei5DMkU4NTY1QUFGQTYwMDE3",
      "snippet": {
        "publishedAt": "2024-03-20T08:26:49Z",
        "channelId": "UCZtzcQ_fiXuw6dNx_AxK7_Q",
        "title": "西野カナ『アイラブユー』 FULL-サブスク全曲解禁記念",
        "description": "サブスク全曲解禁を記念して、『アイラブユー』のMVフルをYouTube初公開！！\n西野カナDL/STREAMING→https://nishinokana.lnk.to/DLST\n\n『アイラブユー』\n2018年4月発売シングル\n2018年11月発売BEST AL「Love Collection 2 ～pink～」収録\n\n■「アイラブユー」歌詞・コード譜面\nhttps://www.ufret.jp/song.php?data=42772\n\nサブスク未配信曲106曲を追加し、全181曲配信中！\nこれまで配信していたシングル表題曲・アルバムリード曲・ベストアルバム“75曲”に加え、未配信だったアルバム曲・カップリング曲・ベストアルバム新録曲など“106曲”を追加。西野カナの楽曲【全181曲】がサブスクで聴けるようになりました！\n\n【未配信曲追加・全曲解禁によって変わること】\n・オリジナルアルバムが、1枚の作品として通して聴けるようになります。\n・シングルパッケージが、カップリング曲も含めて通して聴けるようになります。\n・ベストアルバムも、新録曲を含めて通して聴けるようになります。\n・プレイリストのバリエーションが広がります。\n・これまで未配信だったSpotifyの配信もスタート。\n\n“恋する気持ちをもう一度”\nサブスクで西野カナを聴こう。\n\n■サブスク・ダウンロード\nhttps://nishinokana.lnk.to/DLST\n■CD・DVD・Blu-rayパッケージ\nhttps://www.sonymusicshop.jp/m/arti/artiItm.php?site=S&ima=3019&cd=70005022\n■西野カナOfficial Site\nhttp://www.nishinokana.com/\n■公式SNS\n[Twitter] https://twitter.com/kanayanofficial\n[Facebook] https://ja-jp.facebook.com/nishinokanaofficial\n\n＃西野カナサブスク全曲解禁 #西野カナとドライブなう #恋する気持ちをもう一度",
        "thumbnails": {
          "default": {
            "url": "https://i.ytimg.com/vi/d7U2cyXBgj0/default.jpg",
            "width": 120,
            "height": 90
          },
          "medium": {
            "url": "https://i.ytimg.com/vi/d7U2cyXBgj0/mqdefault.jpg",
            "width": 320,
            "height": 180
          },
          "high": {
            "url": "https://i.ytimg.com/vi/d7U2cyXBgj0/hqdefault.jpg",
            "width": 480,
            "height": 360
          },
          "standard": {
            "url": "https://i.ytimg.com/vi/d7U2cyXBgj0/sddefault.jpg",
            "width": 640,
            "height": 480
          },
          "maxres": {
            "url": "https://i.ytimg.com/vi/d7U2cyXBgj0/maxresdefault.jpg",
            "width": 1280,
            "height": 720
          }
        },
        "channelTitle": "Synera",
        "playlistId": "PLzJ1mqwxogpFuFCk1YfUE1c0gWtnIutfz",
        "position": 25,
        "resourceId": {
          "kind": "youtube#video",
          "videoId": "d7U2cyXBgj0"
        },
        "videoOwnerChannelTitle": "西野カナ Official YouTube Channel",
        "videoOwnerChannelId": "UCXq19VXLNkTtVE9LfRBKd5Q"
      }
    },
    {
      "kind": "youtube#playlistItem",
      "etag": "_1rF3QqT9-JEsQmyLDRh3sl8L38",
      "id": "UEx6SjFtcXd4b2dwRnVGQ2sxWWZVRTFjMGdXdG5JdXRmei44Mjc5REFBRUE2MTdFRDU0",
      "snippet": {
        "publishedAt": "2024-03-20T11:09:19Z",
        "channelId": "UCZtzcQ_fiXuw6dNx_AxK7_Q",
        "title": "美波「アメヲマツ、」MV",
        "description": "美波「アメヲマツ、」MV\nMinami -「 Amewomatsu、」\n\n作詞・作曲：美波\nWords & Music: Minami   \n\nANIMATION：syo5 \n\n2021.7.21(WED) 美波 New CD「DROP」発売\nMinami's New CD \"DROP\" will be released July 21, 2021 (Wed) .\n\nStreaming platforms→https://www.373official.com/pages/5010500/page_202106092252\n\nCD SHOP→https://warnermusicjapan.lnk.to/DROP\nOverseas sales→https://www.cdjapan.co.jp/person/700823407\n\n\nVocal & Electric Guitar: Minami\nElectric Guitar: Takumi Otsuka\nStrings Arrangement & Piano: Taro Makido\nBass: Shige Murata \nDrums: Takashi Kashikura\nStrings: Anzu Suhara Strings\n\nMusical Director & Mixing Engineer: Yoshio Tamamura\n\nRecording Engineer: Masahiro Tamoto\nMastering Engineer: Brian Lucey\n\n\nManagement: Water Reflection\nLabel A&R:  Kazuhito Toyonaga\n\nInstrumental Technician: Koji Watanabe",
        "thumbnails": {
          "default": {
            "url": "https://i.ytimg.com/vi/766qmHTc2ro/default.jpg",
            "width": 120,
            "height": 90
          },
          "medium": {
            "url": "https://i.ytimg.com/vi/766qmHTc2ro/mqdefault.jpg",
            "width": 320,
            "height": 180
          },
          "high": {
            "url": "https://i.ytimg.com/vi/766qmHTc2ro/hqdefault.jpg",
            "width": 480,
            "height": 360
          },
          "standard": {
            "url": "https://i.ytimg.com/vi/766qmHTc2ro/sddefault.jpg",
            "width": 640,
            "height": 480
          },
          "maxres": {
            "url": "https://i.ytimg.com/vi/766qmHTc2ro/maxresdefault.jpg",
            "width": 1280,
            "height": 720
          }
        },
        "channelTitle": "Synera",
        "playlistId": "PLzJ1mqwxogpFuFCk1YfUE1c0gWtnIutfz",
        "position": 26,
        "resourceId": {
          "kind": "youtube#video",
          "videoId": "766qmHTc2ro"
        },
        "videoOwnerChannelTitle": "美波",
        "videoOwnerChannelId": "UC2JzylaIF8qeowc7-5VwwmA"
      }
    },
    {
      "kind": "youtube#playlistItem",
      "etag": "-nxMTu8cJAT0twpdMOAHuP8fY1s",
      "id": "UEx6SjFtcXd4b2dwRnVGQ2sxWWZVRTFjMGdXdG5JdXRmei43NDhFRTgwOTRERTU4Rjg3",
      "snippet": {
        "publishedAt": "2024-03-20T11:11:07Z",
        "channelId": "UCZtzcQ_fiXuw6dNx_AxK7_Q",
        "title": "YOASOBI「勇者」 Official Music Video／TVアニメ『葬送のフリーレン』オープニングテーマ",
        "description": "Streaming & Download : https://orcd.co/yuusha_0929\nMusic : Ayase (https://twitter.com/ayase_0404)\nVocal : ikura (https://twitter.com/ikutalilas)\n\nBackground Chorus English Lyrics：Konnie Aoki\nBackground Chorus：Imani J Dawson / Ebony Bowens / Mimiko Goldstein / Marrista / Sofia Ray / Shore Cienna / Haley Lewis / Jonas Gen Whitaker / Missy Suzuki / Ivy / Velvet / Emily\n\n★インスト音源はこちら\nhttps://piapro.jp/t/WpGM\n\n「勇者」原作小説『奏送』（著：木曾次郎、監修：山田鐘人）\n9/29(金)23時00分同時公開\nhttps://frieren-anime.jp/special/novel/\n\n○TVアニメ『葬送のフリーレン』オープニングテーマ「勇者」\n\nTVアニメ『葬送のフリーレン』\n2023年9月29日(金)よる9時\n日本テレビ系【金曜ロードショー】にて\n「初回2時間スペシャル ～旅立ちの章～」放送 ※一部地域を除く\n以降 10月6日より日本テレビ系 毎週金曜夜11時\n「FRIDAY ANIME NIGHT(フラアニ)」にて放送\nhttp://frieren-anime.jp\n\n©️山田鐘人・アベツカサ／小学館／「葬送のフリーレン」製作委員会\n\n--\nまるで御伽の話 \n終わり迎えた証 \n長過ぎる旅路から \n切り出した一節 \nそれはかつてこの地に \n影を落とした悪を \n討ち取りし勇者との \n短い旅の記憶 \n\n物語は終わり \n勇者は眠りにつく \n穏やかな日常を \nこの地に残して \n時の流れは無情に \n人を忘れさせる \nそこに生きた軌跡も \n錆び付いていく \n\nそれでも君の \n言葉も願いも勇気も \n今も確かに私の中で \n生きている \n\n同じ途を選んだ \nそれだけだったはずなのに \nいつの間にかどうして \n頬を伝う涙の理由をもっと \n知りたいんだ \n今更だって \n共に歩んだ旅路を辿れば \nそこに君は居なくとも \nきっと見つけられる \n\n物語は続く \n一人の旅へと発つ \n立ち寄る街で出会う \n人の記憶の中に残る君は\n\n相も変わらずお人好しで \n格好つけてばかりだね \nあちらこちらに作ったシンボルは \n勝ち取った平和の証 \nそれすら \n未来でいつか \n私が一人にならないように \nあの旅を思い出せるように \n残された目印 \n\nまるで御伽の話 \n終わり迎えた証 \n私を変えた出会い \n百分の一の旅路 \n\n君の勇気をいつか \n風がさらって \n誰の記憶から消えてしまっても \n私が未来に連れて行くから \n\n君の手を取った \nあの日全て始まった \nくだらなくて \n思わずふっと笑ってしまうような \nありふれた時間が今も眩しい \n知りたいんだ \n今更だって \n振り返るとそこにはいつでも \n優しく微笑みかける \n君がいるから \n新たな旅の始まりは \n君が守り抜いたこの地に \n芽吹いた命と共に\n--\n○Music Video Staff\n原作：山田鐘人・アベツカサ「葬送のフリーレン」（小学館「週刊少年サンデー」連載中） \n監督：斎藤圭一郎　シリーズ構成：鈴木智尋　キャラクターデザイン・総作画監督：長澤礼子\nコンセプトアート：吉岡誠子　魔物デザイン：原科大樹　アクションディレクター：岩澤亨\nデザインワークス：簑島綾香 山﨑絵美 とだま。 長坂慶太 亀澤蘭 松村佳子 高瀬丸　美術監督：高木佐和子　美術設定：杉山晋史\n色彩設計：大野春恵　3DCGディレクター：廣住茂徳　撮影監督：伏原あかね　編集：木村佳史子\n音響監督：はたしょう二　音楽：Evan Call　アニメーション制作：マッドハウス\n\n\n原画\n廣江啓輔　堀　雅歩　原野瑠奈　神取万由子\n河野敏弥　内山玄基　藤本航己　佐藤綾花\n柿木田隼人　無意　　　李　鑑修　油布京子\n平田有加　三輪和宏　亀澤　蘭　八重樫優翼\n吉田奏子　山﨑絵美　おだし　　辻　彩夏\n川瀬蛍 (Kinema citrus)   松村佳子　小橋弘侑\n永野裕大　原科大樹　小笠原真\n\n\nレイアウト\n吉岡誠子\n\n第二原画\n佐藤利幸\n\n動画検査\n大口　茜　小林央奈　小杉あかり\n\n動画\nマッドハウス\n三浦彩由　瀧本智美　張    伊人　山脇僚太\n永山章太郎　大西夕海　山中加奈子　田代彩菜\n本間達也　小泉郁乃　坂詰かよ　千田桃花\n石　帆　　趙　翊彤　鈴木渚沙　木村かのう\nDR MOVIE　MAA MOPICS　光の園・アニメーション\n\n色彩設計・色指定・仕上げ検査\n大野春恵\n\n仕上げ\nスタジオエル　DR MOVIE　MAA MOPICS　光の園・アニメーション\n\n美術監督\n丸山由紀子\n\n背景\nアトリエ・ムサ\n丸山由紀子　竹越輝子　小嶋しず子\n山梨絵里　組嶽江里　高橋映莉加\n吉野翔太郎　佐藤那美　柳瀬めぐみ\n\n撮影監督\n伏原あかね\n\n撮影監督補佐\n継岡夢月\n\n撮影\nMADBOX\n小田 来夢　中野 美佳\n\n3DCG\nMADBOX\n\n3D監督\n廣住茂徳\n\nCGワークス\nナガハマユウキ\n\nCGプロダクションマネージャー\n森下 裕樹\nサムライピクチャーズ\n\nCGプロデューサー\n谷口 顕也\n\n3DCG制作進行\n山口 亮\n\nモデリングディレクター\n林 和正\n\nCGモデリング\n諏訪美紀子　波多野樹朗　喜田祐輔\n\n編集\n木村佳史子\n\nタイポグラフィクス\n武山篤(STUDIO MASSKET)\n\nアニメーションプロデューサ―\n福士裕一郎\n\n制作デスク\n早川紗良\n\nアニメーション制作\nマッドハウス\n\n製作\n「葬送のフリーレン」製作委員会\n\nMVディレクター・絵コンテ・演出\n廣江啓輔\n\n作画監督\n高瀬丸\n--\n#YOASOBI #勇者 #葬送のフリーレン",
        "thumbnails": {
          "default": {
            "url": "https://i.ytimg.com/vi/OIBODIPC_8Y/default.jpg",
            "width": 120,
            "height": 90
          },
          "medium": {
            "url": "https://i.ytimg.com/vi/OIBODIPC_8Y/mqdefault.jpg",
            "width": 320,
            "height": 180
          },
          "high": {
            "url": "https://i.ytimg.com/vi/OIBODIPC_8Y/hqdefault.jpg",
            "width": 480,
            "height": 360
          },
          "standard": {
            "url": "https://i.ytimg.com/vi/OIBODIPC_8Y/sddefault.jpg",
            "width": 640,
            "height": 480
          },
          "maxres": {
            "url": "https://i.ytimg.com/vi/OIBODIPC_8Y/maxresdefault.jpg",
            "width": 1280,
            "height": 720
          }
        },
        "channelTitle": "Synera",
        "playlistId": "PLzJ1mqwxogpFuFCk1YfUE1c0gWtnIutfz",
        "position": 27,
        "resourceId": {
          "kind": "youtube#video",
          "videoId": "OIBODIPC_8Y"
        },
        "videoOwnerChannelTitle": "Ayase / YOASOBI",
        "videoOwnerChannelId": "UCvpredjG93ifbCP1Y77JyFA"
      }
    },
    {
      "kind": "youtube#playlistItem",
      "etag": "bvH8ETtn1snAGUxn5m8tf57L8rE",
      "id": "UEx6SjFtcXd4b2dwRnVGQ2sxWWZVRTFjMGdXdG5JdXRmei41QUZGQTY5OTE4QTREQUU4",
      "snippet": {
        "publishedAt": "2024-03-26T08:47:24Z",
        "channelId": "UCZtzcQ_fiXuw6dNx_AxK7_Q",
        "title": "幾田りら「Answer」 from MTV Unplugged: Lilas Ikuta",
        "description": "3月8日(水)発売 1st ALBUM『Sketch』初回生産限定盤Blu-ray収録、昨年11月放送「MTV Unplugged: Lilas Ikuta」より「Answer」映像を公開。\n\n・・・・・\n2023年3月8日(水)リリース\n幾田りら 1st ALBUM『Sketch』\nhttps://lnk.to/sl3grE\n\n《収録曲》 ※初回生産限定盤・通常盤共通\n1. Answer (東京海上日動あんしん生命「あんしん就業不能保障保険」ＣＭソング)\n2. サークル (クラレ企業広告「きっと明日も、ハレ、クラレ。 」 CMソング)\n3. スパークル (ABEMA『今日、好きになりました。』主題歌)\n4. Midnight Talk\n5. 蒲公英 (NHKドラマ10『大奥』主題歌)\n6. JUMP (フジテレビ系『FIFAワールドカップ カタール2022』番組公式テーマソング)\n7. レンズ (TBS系 火曜ドラマ『持続可能な恋ですか？〜父と娘の結婚行進曲〜』主題歌)\n8. 吉祥寺\n9. ヒカリ (KISSME主催「会ったことあるのに、はじめまして」プロジェクト書き下ろしソング)\n10. 宝石\n11. ロマンスの約束 (ABEMA『今日、好きになりました。』主題歌)\n12. スパークル - From THE FIRST TAKE　※CD限定収録\n13. レンズ - From THE FIRST TAKE　※CD限定収録\n\n■初回生産限定盤\n仕様：CD＋Blu-ray／価格：4,500円＋税／品番：XSCL-67～8\n[Blu-ray 収録内容]\n2022年11月に行われたソロライブ「MTV Unplugged: Lilas Ikuta」\n《セットリスト》\n1. ヒカリ\n2. ロマンスの約束\n3. おもかげ\n4. JUMP\n5. レンズ\n6. 怪獣の腕のなか - Cover\n7. 宝石\n8. Ginger - Cover\n9. スパークル\n10. Answer\n\n■通常盤\n仕様：CD／価格：3,000円＋税／品番：XSCL-69\n\n◆幾田りら コメント\n1stアルバムをリリースします。私にとって詞は心の日記のようなもので、メロディーはその心情が自由に飛んでいくための羽の役割を持っています。日常生活で書き溜めてきた心の機微や内側を、曝け出し、音楽に投影することが、私の楽曲制作の心臓です。この先も幾田りらとして紡ぐ音楽が、ありのままの自分自身を自由に描ける場所で在り続けたいという願いと決意を込めて、アルバムに「Sketch」と名付けました。そしてジャケットには、本作のアートディレクションを担当してくださった村上智香さんと共に、そんな包み隠さない“素の自分”の姿を映しました。耳に触れた時、皆さまの心に寄り添い、そばに置いておきたい音楽であれたら何より嬉しいです。是非手にとって聴いてみてください。\n\n【ライブ概要】\n■幾田りら 1st ワンマンツアー『SKETCH』\n\n7月5日(水) 愛知・Zepp Nagoya　開場 18:00 / 開演 19:00\n[問] サンデーフォークプロモーション　Tel. 052-320-9100 (12:00～18:00)\n\n7月6日(木) 大阪・Zepp Namba　開場 18:00 / 開演 19:00\n[問] キョードーインフォメーション　Tel. 0570-200-888  (11:00～18:00 ※日祝除く)\n\n7月10日(月) 神奈川・KT Zepp Yokohama　開場 18:00 / 開演 19:00\n[問] ホットスタッフ・プロモーション　Tel. 050-5211-6077 (平日12:00〜18:00)\n\n料金：全席指定 6,000円(税込)\n\n★1st アルバム『Sketch』 最速CD封入先行抽選受付\n受付期間：2023月3月7日(火)15:00～4月２日(日)23:59\n当落発表： 2023年４月６日(木)\n枚数制限：シリアルナンバー1件につき1申込み限り。 (1申込み4枚まで)\nアルバム予約はこちら：https://lnk.to/sl3grE\n\n[注意事項]\n※ドリンク代別\n※6歳以上有料。5歳以下膝上鑑賞無料、お席が必要な場合は有料。\n※入場時に身分証確認を実施いたします。本人確認ができない場合は入場をお断りいたします。\n※本公演は新型コロナウイルス感染症対策を徹底し、会場や自治体などのガイドラインに沿って開催致します。\n※公演中止・延期の場合を除き、個人的な体調不良および新型コロナウイルス感染などお客様のご事情による払い戻しはできませんのでご了承ください。\n※客席を含む会場内の映像・写真が公開されることがあります。\n\n【店舗別特典 対象店舗/特典内容】\n店舗別の全9種の特典となります。是非お早めにご予約ください！\n\n■幾田りら応援店　・・・　『Sketch』オリジナルステッカー\n■Sony Music Shop　・・・　「Answer」オリジナルステッカー\n■TOWER RECORDS全店（オンライン含む / 一部店舗除く）　・・・　「蒲公英」オリジナルステッカー\n■HMV全店（HMV&BOOKS online含む / 一部店舗を除く）　・・・　「レンズ」オリジナルステッカー\n■TSUTAYA RECORDS（一部店舗除く）/ TSUTAYAオンラインショッピング　・・・　「スパークル」オリジナルステッカー\n■WonderGOO / 新星堂（一部店舗除く）および新星堂WonderGOOオンライン　・・・　「ヒカリ」オリジナルステッカー\n■Amazon.co.jp　・・・　『Sketch』オリジナルメガジャケ\n■楽天ブックス　・・・　「JUMP」オリジナルステッカー\n■セブンネットショッピング　・・・　「ロマンスの約束」オリジナルステッカー\n\n★応援店対象店舗リスト\nhttps://lilasikuta.jp/shoplist/230308/\n\n※数に限りがありますので、なくなり次第終了となります。\n※初回生産限定盤(XSCL-67~68)・通常盤(XSCL-69)のどちらをご購入いただいても同じ特典をお渡しいたします。\n※上記店舗以外での配布はございません。\n※各オンラインショップにつきまして、カートが公開されるまでに時間がかかる場合がございます。\n※Amazon.co.jp、楽天ブックス、その他一部オンラインショップでは「特典対象商品ページ」と「特典非対象商品ページ」がございます。予約の際は、希望される商品ページであることをご確認ください。\n\n・・・・・\nCreated by ROBERT SMALL & JIM BURNS\n\nProducer / Director：中本敏之 [NOUVELLE MEDIAS]\nDirector：岡﨑愛司 [NOUVELLE MEDIAS]\nAssistant Producer：兼光奈緒 [Paramount]\nChief Producer：戸田裕介 [Paramount]\nSupervising Producer：中山計 [Paramount]\n\n© 2022 Viacom International Inc. All rights Reserved. MTV, MTV logo, Unplugged, and all related titles and logos are trademarks of Viacom International Inc.",
        "thumbnails": {
          "default": {
            "url": "https://i.ytimg.com/vi/gTlpo5HIIZE/default.jpg",
            "width": 120,
            "height": 90
          },
          "medium": {
            "url": "https://i.ytimg.com/vi/gTlpo5HIIZE/mqdefault.jpg",
            "width": 320,
            "height": 180
          },
          "high": {
            "url": "https://i.ytimg.com/vi/gTlpo5HIIZE/hqdefault.jpg",
            "width": 480,
            "height": 360
          },
          "standard": {
            "url": "https://i.ytimg.com/vi/gTlpo5HIIZE/sddefault.jpg",
            "width": 640,
            "height": 480
          },
          "maxres": {
            "url": "https://i.ytimg.com/vi/gTlpo5HIIZE/maxresdefault.jpg",
            "width": 1280,
            "height": 720
          }
        },
        "channelTitle": "Synera",
        "playlistId": "PLzJ1mqwxogpFuFCk1YfUE1c0gWtnIutfz",
        "position": 28,
        "resourceId": {
          "kind": "youtube#video",
          "videoId": "gTlpo5HIIZE"
        },
        "videoOwnerChannelTitle": "幾田りら Official",
        "videoOwnerChannelId": "UCztEY6czNyJKjRWMwuur9bg"
      }
    }
  ],
  "pageInfo": {
    "totalResults": 29,
    "resultsPerPage": 50
  }
}
